{"nm":"Flow 12","ddd":0,"h":1110,"w":1110,"meta":{"g":"LottieFiles Figma v55"},"layers":[{"ty":4,"nm":"Vector 39","sr":1,"st":0,"op":130.06,"ip":0,"hd":false,"ddd":0,"bm":0,"hasMask":false,"ao":0,"ks":{"a":{"a":1,"k":[{"o":{"x":0.32,"y":0},"i":{"x":0.67,"y":0},"s":[34.5,79.5],"t":0},{"o":{"x":0.32,"y":0},"i":{"x":0.67,"y":0},"s":[34.5,79.5],"t":27.06},{"o":{"x":0.32,"y":0},"i":{"x":0.67,"y":0},"s":[34.5,79.5],"t":30},{"o":{"x":0.32,"y":0},"i":{"x":0.67,"y":0},"s":[34.5,79.5],"t":33},{"o":{"x":0.32,"y":0},"i":{"x":0.67,"y":0},"s":[20,45.5],"t":69},{"s":[20,45.5],"t":129}]},"s":{"a":1,"k":[{"o":{"x":0.32,"y":0},"i":{"x":0.67,"y":0},"s":[100,100],"t":0},{"o":{"x":0.32,"y":0},"i":{"x":0.67,"y":0},"s":[100,100],"t":27.06},{"o":{"x":0.32,"y":0},"i":{"x":0.67,"y":0},"s":[100,100],"t":30},{"o":{"x":0.32,"y":0},"i":{"x":0.67,"y":0},"s":[100,100],"t":33},{"o":{"x":0.32,"y":0},"i":{"x":0.67,"y":0},"s":[100,100],"t":69},{"s":[100,100],"t":129}]},"sk":{"a":0,"k":0},"p":{"a":1,"k":[{"o":{"x":0.32,"y":0},"i":{"x":0.67,"y":0},"s":[527.5,650.5],"t":0},{"o":{"x":0.32,"y":0},"i":{"x":0.67,"y":0},"s":[527.5,650.5],"t":27.06},{"o":{"x":0.32,"y":0},"i":{"x":0.67,"y":0},"s":[527.5,650.5],"t":30},{"o":{"x":0.32,"y":0},"i":{"x":0.67,"y":0},"s":[527.5,650.5],"t":33},{"o":{"x":0.32,"y":0},"i":{"x":0.67,"y":0},"s":[519,624.5],"t":69},{"s":[519,624.5],"t":129}]},"r":{"a":1,"k":[{"o":{"x":0.32,"y":0},"i":{"x":0.67,"y":0},"s":[0],"t":0},{"o":{"x":0.32,"y":0},"i":{"x":0.67,"y":0},"s":[0],"t":27.06},{"o":{"x":0.32,"y":0},"i":{"x":0.67,"y":0},"s":[0],"t":30},{"o":{"x":0.32,"y":0},"i":{"x":0.67,"y":0},"s":[0],"t":33},{"o":{"x":0.32,"y":0},"i":{"x":0.67,"y":0},"s":[0],"t":69},{"s":[0],"t":129}]},"sa":{"a":0,"k":0},"o":{"a":1,"k":[{"o":{"x":0.32,"y":0},"i":{"x":0.67,"y":0},"s":[0],"t":0},{"o":{"x":0.32,"y":0},"i":{"x":0.67,"y":0},"s":[0],"t":27.06},{"o":{"x":0.32,"y":0},"i":{"x":0.67,"y":0},"s":[100],"t":30},{"o":{"x":0.32,"y":0},"i":{"x":0.67,"y":0},"s":[100],"t":33},{"o":{"x":0.32,"y":0},"i":{"x":0.67,"y":0},"s":[100],"t":69},{"s":[100],"t":129}]}},"shapes":[{"ty":"sh","bm":0,"hd":false,"nm":"","d":1,"ks":{"a":1,"k":[{"o":{"x":0.32,"y":0},"i":{"x":0.67,"y":0},"s":[{"c":true,"i":[[0,0],[0,0],[8.38,-61.43],[0,0],[-5.83,22.36],[3.59,-30.54],[0,0],[-14.74,44.12]],"o":[[0,0],[-11.72,60.1],[0,0],[4.51,-21.68],[-2.5,18.1],[0,0],[5.57,-70.16],[0,0]],"v":[[69,11.27],[26.63,0],[0,155.24],[3.63,155.24],[16.95,98.91],[9.68,155.24],[43.58,159],[69,11.27]]}],"t":0},{"o":{"x":0.32,"y":0},"i":{"x":0.67,"y":0},"s":[{"c":true,"i":[[0,0],[0,0],[8.38,-61.43],[0,0],[-5.83,22.36],[3.59,-30.54],[0,0],[-14.74,44.12]],"o":[[0,0],[-11.72,60.1],[0,0],[4.51,-21.68],[-2.5,18.1],[0,0],[5.57,-70.16],[0,0]],"v":[[69,11.27],[26.63,0],[0,155.24],[3.63,155.24],[16.95,98.91],[9.68,155.24],[43.58,159],[69,11.27]]}],"t":27.06},{"o":{"x":0.32,"y":0},"i":{"x":0.67,"y":0},"s":[{"c":true,"i":[[0,0],[0,0],[8.38,-61.43],[0,0],[-5.83,22.36],[3.59,-30.54],[0,0],[-14.74,44.12]],"o":[[0,0],[-11.72,60.1],[0,0],[4.51,-21.68],[-2.5,18.1],[0,0],[5.57,-70.16],[0,0]],"v":[[69,11.27],[26.63,0],[0,155.24],[3.63,155.24],[16.95,98.91],[9.68,155.24],[43.58,159],[69,11.27]]}],"t":30},{"o":{"x":0.32,"y":0},"i":{"x":0.67,"y":0},"s":[{"c":true,"i":[[0,0],[0,0],[8.38,-61.43],[0,0],[-5.83,22.36],[3.59,-30.54],[0,0],[-14.74,44.12]],"o":[[0,0],[-11.72,60.1],[0,0],[4.51,-21.68],[-2.5,18.1],[0,0],[5.57,-70.16],[0,0]],"v":[[69,11.27],[26.63,0],[0,155.24],[3.63,155.24],[16.95,98.91],[9.68,155.24],[43.58,159],[69,11.27]]}],"t":33},{"o":{"x":0.32,"y":0},"i":{"x":0.67,"y":0},"s":[{"c":true,"i":[[0,0],[0,0],[4.86,-35.16],[0,0],[-3.38,12.8],[2.08,-17.48],[0,0],[-8.54,25.25]],"o":[[0,0],[-6.79,34.4],[0,0],[2.61,-12.41],[-1.45,10.36],[0,0],[3.23,-40.16],[0,0]],"v":[[40,6.45],[15.44,0],[0,88.85],[2.11,88.85],[9.82,56.61],[5.61,88.85],[25.26,91],[40,6.45]]}],"t":69},{"s":[{"c":true,"i":[[0,0],[0,0],[4.86,-35.16],[0,0],[-3.38,12.8],[2.08,-17.48],[0,0],[-8.54,25.25]],"o":[[0,0],[-6.79,34.4],[0,0],[2.61,-12.41],[-1.45,10.36],[0,0],[3.23,-40.16],[0,0]],"v":[[40,6.45],[15.44,0],[0,88.85],[2.11,88.85],[9.82,56.61],[5.61,88.85],[25.26,91],[40,6.45]]}],"t":129}]}},{"ty":"fl","bm":0,"hd":false,"nm":"","c":{"a":1,"k":[{"o":{"x":0.32,"y":0},"i":{"x":0.67,"y":0},"s":[0.2902,0.6,0.3765],"t":0},{"o":{"x":0.32,"y":0},"i":{"x":0.67,"y":0},"s":[0.2902,0.6,0.3765],"t":27.06},{"o":{"x":0.32,"y":0},"i":{"x":0.67,"y":0},"s":[0.2902,0.6,0.3765],"t":30},{"o":{"x":0.32,"y":0},"i":{"x":0.67,"y":0},"s":[0.2902,0.6,0.3765],"t":33},{"o":{"x":0.32,"y":0},"i":{"x":0.67,"y":0},"s":[0.2902,0.6,0.3765],"t":69},{"s":[0.2902,0.6,0.3765],"t":129}]},"r":1,"o":{"a":1,"k":[{"o":{"x":0.32,"y":0},"i":{"x":0.67,"y":0},"s":[100],"t":0},{"o":{"x":0.32,"y":0},"i":{"x":0.67,"y":0},"s":[100],"t":27.06},{"o":{"x":0.32,"y":0},"i":{"x":0.67,"y":0},"s":[100],"t":30},{"o":{"x":0.32,"y":0},"i":{"x":0.67,"y":0},"s":[100],"t":33},{"o":{"x":0.32,"y":0},"i":{"x":0.67,"y":0},"s":[100],"t":69},{"s":[100],"t":129}]}}],"ind":1},{"ty":4,"nm":"Vector 32","sr":1,"st":0,"op":130.06,"ip":0,"hd":false,"ddd":0,"bm":0,"hasMask":false,"ao":0,"ks":{"a":{"a":1,"k":[{"o":{"x":0.32,"y":0},"i":{"x":0.67,"y":0},"s":[35,109],"t":0},{"o":{"x":0.32,"y":0},"i":{"x":0.67,"y":0},"s":[35,109],"t":12.06},{"o":{"x":0.32,"y":0},"i":{"x":0.67,"y":0},"s":[35,109],"t":18},{"o":{"x":0.32,"y":0},"i":{"x":0.67,"y":0},"s":[35,109],"t":21},{"o":{"x":0.32,"y":0},"i":{"x":0.67,"y":0},"s":[35,109],"t":24},{"o":{"x":0.32,"y":0},"i":{"x":0.67,"y":0},"s":[35,109],"t":27},{"o":{"x":0.32,"y":0},"i":{"x":0.67,"y":0},"s":[35,109],"t":30},{"o":{"x":0.32,"y":0},"i":{"x":0.67,"y":0},"s":[35,109],"t":33},{"o":{"x":0.32,"y":0},"i":{"x":0.67,"y":0},"s":[20,62.5],"t":69},{"s":[20,62.5],"t":129}]},"s":{"a":1,"k":[{"o":{"x":0.32,"y":0},"i":{"x":0.67,"y":0},"s":[100,100],"t":0},{"o":{"x":0.32,"y":0},"i":{"x":0.67,"y":0},"s":[100,100],"t":12.06},{"o":{"x":0.32,"y":0},"i":{"x":0.67,"y":0},"s":[100,100],"t":18},{"o":{"x":0.32,"y":0},"i":{"x":0.67,"y":0},"s":[100,100],"t":21},{"o":{"x":0.32,"y":0},"i":{"x":0.67,"y":0},"s":[100,100],"t":24},{"o":{"x":0.32,"y":0},"i":{"x":0.67,"y":0},"s":[100,100],"t":27},{"o":{"x":0.32,"y":0},"i":{"x":0.67,"y":0},"s":[100,100],"t":30},{"o":{"x":0.32,"y":0},"i":{"x":0.67,"y":0},"s":[100,100],"t":33},{"o":{"x":0.32,"y":0},"i":{"x":0.67,"y":0},"s":[100,100],"t":69},{"s":[100,100],"t":129}]},"sk":{"a":0,"k":0},"p":{"a":1,"k":[{"o":{"x":0.32,"y":0},"i":{"x":0.67,"y":0},"s":[451,556],"t":0},{"o":{"x":0.32,"y":0},"i":{"x":0.67,"y":0},"s":[451,556],"t":12.06},{"o":{"x":0.32,"y":0},"i":{"x":0.67,"y":0},"s":[451,556],"t":18},{"o":{"x":0.32,"y":0},"i":{"x":0.67,"y":0},"s":[451,556],"t":21},{"o":{"x":0.32,"y":0},"i":{"x":0.67,"y":0},"s":[451,556],"t":24},{"o":{"x":0.32,"y":0},"i":{"x":0.67,"y":0},"s":[451,556],"t":27},{"o":{"x":0.32,"y":0},"i":{"x":0.67,"y":0},"s":[451,556],"t":30},{"o":{"x":0.32,"y":0},"i":{"x":0.67,"y":0},"s":[451,556],"t":33},{"o":{"x":0.32,"y":0},"i":{"x":0.67,"y":0},"s":[475,570.5],"t":69},{"s":[475,570.5],"t":129}]},"r":{"a":1,"k":[{"o":{"x":0.32,"y":0},"i":{"x":0.67,"y":0},"s":[0],"t":0},{"o":{"x":0.32,"y":0},"i":{"x":0.67,"y":0},"s":[0],"t":12.06},{"o":{"x":0.32,"y":0},"i":{"x":0.67,"y":0},"s":[0],"t":18},{"o":{"x":0.32,"y":0},"i":{"x":0.67,"y":0},"s":[0],"t":21},{"o":{"x":0.32,"y":0},"i":{"x":0.67,"y":0},"s":[0],"t":24},{"o":{"x":0.32,"y":0},"i":{"x":0.67,"y":0},"s":[0],"t":27},{"o":{"x":0.32,"y":0},"i":{"x":0.67,"y":0},"s":[0],"t":30},{"o":{"x":0.32,"y":0},"i":{"x":0.67,"y":0},"s":[0],"t":33},{"o":{"x":0.32,"y":0},"i":{"x":0.67,"y":0},"s":[0],"t":69},{"s":[0],"t":129}]},"sa":{"a":0,"k":0},"o":{"a":1,"k":[{"o":{"x":0.32,"y":0},"i":{"x":0.67,"y":0},"s":[0],"t":0},{"o":{"x":0.32,"y":0},"i":{"x":0.67,"y":0},"s":[0],"t":12.06},{"o":{"x":0.32,"y":0},"i":{"x":0.67,"y":0},"s":[100],"t":18},{"o":{"x":0.32,"y":0},"i":{"x":0.67,"y":0},"s":[100],"t":21},{"o":{"x":0.32,"y":0},"i":{"x":0.67,"y":0},"s":[100],"t":24},{"o":{"x":0.32,"y":0},"i":{"x":0.67,"y":0},"s":[100],"t":27},{"o":{"x":0.32,"y":0},"i":{"x":0.67,"y":0},"s":[100],"t":30},{"o":{"x":0.32,"y":0},"i":{"x":0.67,"y":0},"s":[100],"t":33},{"o":{"x":0.32,"y":0},"i":{"x":0.67,"y":0},"s":[100],"t":69},{"s":[100],"t":129}]}},"shapes":[{"ty":"sh","bm":0,"hd":false,"nm":"","d":1,"ks":{"a":1,"k":[{"o":{"x":0.32,"y":0},"i":{"x":0.67,"y":0},"s":[{"c":true,"i":[[0,0],[0,0],[2.87,-83.6],[0,0],[-5.03,32.15],[-0.77,-31.47],[0,0],[-5.19,89.44]],"o":[[0,0],[3.9,87.04],[0,0],[4.3,-31.37],[-0.59,32.01],[0,0],[-4.21,-81.68],[0,0]],"v":[[70,0],[0,0],[0,218],[5,218],[16.25,136.88],[16.25,218],[70,218],[70,0]]}],"t":0},{"o":{"x":0.32,"y":0},"i":{"x":0.67,"y":0},"s":[{"c":true,"i":[[0,0],[0,0],[2.87,-83.6],[0,0],[-5.03,32.15],[-0.77,-31.47],[0,0],[-5.19,89.44]],"o":[[0,0],[3.9,87.04],[0,0],[4.3,-31.37],[-0.59,32.01],[0,0],[-4.21,-81.68],[0,0]],"v":[[70,0],[0,0],[0,218],[5,218],[16.25,136.88],[16.25,218],[70,218],[70,0]]}],"t":12.06},{"o":{"x":0.32,"y":0},"i":{"x":0.67,"y":0},"s":[{"c":true,"i":[[0,0],[0,0],[2.87,-83.6],[0,0],[-5.03,32.15],[-0.77,-31.47],[0,0],[-5.19,89.44]],"o":[[0,0],[3.9,87.04],[0,0],[4.3,-31.37],[-0.59,32.01],[0,0],[-4.21,-81.68],[0,0]],"v":[[70,0],[0,0],[0,218],[5,218],[16.25,136.88],[16.25,218],[70,218],[70,0]]}],"t":18},{"o":{"x":0.32,"y":0},"i":{"x":0.67,"y":0},"s":[{"c":true,"i":[[0,0],[0,0],[2.87,-83.6],[0,0],[-5.03,32.15],[-0.77,-31.47],[0,0],[-5.19,89.44]],"o":[[0,0],[3.9,87.04],[0,0],[4.3,-31.37],[-0.59,32.01],[0,0],[-4.21,-81.68],[0,0]],"v":[[70,0],[0,0],[0,218],[5,218],[16.25,136.88],[16.25,218],[70,218],[70,0]]}],"t":21},{"o":{"x":0.32,"y":0},"i":{"x":0.67,"y":0},"s":[{"c":true,"i":[[0,0],[0,0],[2.87,-83.6],[0,0],[-5.03,32.15],[-0.77,-31.47],[0,0],[-5.19,89.44]],"o":[[0,0],[3.9,87.04],[0,0],[4.3,-31.37],[-0.59,32.01],[0,0],[-4.21,-81.68],[0,0]],"v":[[70,0],[0,0],[0,218],[5,218],[16.25,136.88],[16.25,218],[70,218],[70,0]]}],"t":24},{"o":{"x":0.32,"y":0},"i":{"x":0.67,"y":0},"s":[{"c":true,"i":[[0,0],[0,0],[2.87,-83.6],[0,0],[-5.03,32.15],[-0.77,-31.47],[0,0],[-5.19,89.44]],"o":[[0,0],[3.9,87.04],[0,0],[4.3,-31.37],[-0.59,32.01],[0,0],[-4.21,-81.68],[0,0]],"v":[[70,0],[0,0],[0,218],[5,218],[16.25,136.88],[16.25,218],[70,218],[70,0]]}],"t":27},{"o":{"x":0.32,"y":0},"i":{"x":0.67,"y":0},"s":[{"c":true,"i":[[0,0],[0,0],[2.87,-83.6],[0,0],[-5.03,32.15],[-0.77,-31.47],[0,0],[-5.19,89.44]],"o":[[0,0],[3.9,87.04],[0,0],[4.3,-31.37],[-0.59,32.01],[0,0],[-4.21,-81.68],[0,0]],"v":[[70,0],[0,0],[0,218],[5,218],[16.25,136.88],[16.25,218],[70,218],[70,0]]}],"t":30},{"o":{"x":0.32,"y":0},"i":{"x":0.67,"y":0},"s":[{"c":true,"i":[[0,0],[0,0],[2.87,-83.6],[0,0],[-5.03,32.15],[-0.77,-31.47],[0,0],[-5.19,89.44]],"o":[[0,0],[3.9,87.04],[0,0],[4.3,-31.37],[-0.59,32.01],[0,0],[-4.21,-81.68],[0,0]],"v":[[70,0],[0,0],[0,218],[5,218],[16.25,136.88],[16.25,218],[70,218],[70,0]]}],"t":33},{"o":{"x":0.32,"y":0},"i":{"x":0.67,"y":0},"s":[{"c":true,"i":[[0,0],[0,0],[1.64,-47.93],[0,0],[-2.87,18.43],[-0.44,-18.04],[0,0],[-2.96,51.28]],"o":[[0,0],[2.23,49.91],[0,0],[2.46,-17.99],[-0.34,18.35],[0,0],[-2.41,-46.83],[0,0]],"v":[[40,0],[0,0],[0,125],[2.86,125],[9.29,78.49],[9.29,125],[40,125],[40,0]]}],"t":69},{"s":[{"c":true,"i":[[0,0],[0,0],[1.64,-47.93],[0,0],[-2.87,18.43],[-0.44,-18.04],[0,0],[-2.96,51.28]],"o":[[0,0],[2.23,49.91],[0,0],[2.46,-17.99],[-0.34,18.35],[0,0],[-2.41,-46.83],[0,0]],"v":[[40,0],[0,0],[0,125],[2.86,125],[9.29,78.49],[9.29,125],[40,125],[40,0]]}],"t":129}]}},{"ty":"fl","bm":0,"hd":false,"nm":"","c":{"a":1,"k":[{"o":{"x":0.32,"y":0},"i":{"x":0.67,"y":0},"s":[0.2902,0.6,0.3765],"t":0},{"o":{"x":0.32,"y":0},"i":{"x":0.67,"y":0},"s":[0.2902,0.6,0.3765],"t":12.06},{"o":{"x":0.32,"y":0},"i":{"x":0.67,"y":0},"s":[0.2902,0.6,0.3765],"t":18},{"o":{"x":0.32,"y":0},"i":{"x":0.67,"y":0},"s":[0.2902,0.6,0.3765],"t":21},{"o":{"x":0.32,"y":0},"i":{"x":0.67,"y":0},"s":[0.2902,0.6,0.3765],"t":24},{"o":{"x":0.32,"y":0},"i":{"x":0.67,"y":0},"s":[0.2902,0.6,0.3765],"t":27},{"o":{"x":0.32,"y":0},"i":{"x":0.67,"y":0},"s":[0.2902,0.6,0.3765],"t":30},{"o":{"x":0.32,"y":0},"i":{"x":0.67,"y":0},"s":[0.2902,0.6,0.3765],"t":33},{"o":{"x":0.32,"y":0},"i":{"x":0.67,"y":0},"s":[0.2902,0.6,0.3765],"t":69},{"s":[0.2902,0.6,0.3765],"t":129}]},"r":1,"o":{"a":1,"k":[{"o":{"x":0.32,"y":0},"i":{"x":0.67,"y":0},"s":[100],"t":0},{"o":{"x":0.32,"y":0},"i":{"x":0.67,"y":0},"s":[100],"t":12.06},{"o":{"x":0.32,"y":0},"i":{"x":0.67,"y":0},"s":[100],"t":18},{"o":{"x":0.32,"y":0},"i":{"x":0.67,"y":0},"s":[100],"t":21},{"o":{"x":0.32,"y":0},"i":{"x":0.67,"y":0},"s":[100],"t":24},{"o":{"x":0.32,"y":0},"i":{"x":0.67,"y":0},"s":[100],"t":27},{"o":{"x":0.32,"y":0},"i":{"x":0.67,"y":0},"s":[100],"t":30},{"o":{"x":0.32,"y":0},"i":{"x":0.67,"y":0},"s":[100],"t":33},{"o":{"x":0.32,"y":0},"i":{"x":0.67,"y":0},"s":[100],"t":69},{"s":[100],"t":129}]}}],"ind":2},{"ty":4,"nm":"Vector 33","sr":1,"st":0,"op":130.06,"ip":0,"hd":false,"ddd":0,"bm":0,"hasMask":false,"ao":0,"ks":{"a":{"a":1,"k":[{"o":{"x":0.32,"y":0},"i":{"x":0.67,"y":0},"s":[35,108.5],"t":0},{"o":{"x":0.32,"y":0},"i":{"x":0.67,"y":0},"s":[35,108.5],"t":18.06},{"o":{"x":0.32,"y":0},"i":{"x":0.67,"y":0},"s":[35,108.5],"t":21},{"o":{"x":0.32,"y":0},"i":{"x":0.67,"y":0},"s":[35,108.5],"t":24},{"o":{"x":0.32,"y":0},"i":{"x":0.67,"y":0},"s":[35,108.5],"t":27},{"o":{"x":0.32,"y":0},"i":{"x":0.67,"y":0},"s":[35,108.5],"t":30},{"o":{"x":0.32,"y":0},"i":{"x":0.67,"y":0},"s":[35,108.5],"t":33},{"o":{"x":0.32,"y":0},"i":{"x":0.67,"y":0},"s":[20,62],"t":69},{"s":[20,62],"t":129}]},"s":{"a":1,"k":[{"o":{"x":0.32,"y":0},"i":{"x":0.67,"y":0},"s":[100,100],"t":0},{"o":{"x":0.32,"y":0},"i":{"x":0.67,"y":0},"s":[100,100],"t":18.06},{"o":{"x":0.32,"y":0},"i":{"x":0.67,"y":0},"s":[100,100],"t":21},{"o":{"x":0.32,"y":0},"i":{"x":0.67,"y":0},"s":[100,100],"t":24},{"o":{"x":0.32,"y":0},"i":{"x":0.67,"y":0},"s":[100,100],"t":27},{"o":{"x":0.32,"y":0},"i":{"x":0.67,"y":0},"s":[100,100],"t":30},{"o":{"x":0.32,"y":0},"i":{"x":0.67,"y":0},"s":[100,100],"t":33},{"o":{"x":0.32,"y":0},"i":{"x":0.67,"y":0},"s":[100,100],"t":69},{"s":[100,100],"t":129}]},"sk":{"a":0,"k":0},"p":{"a":1,"k":[{"o":{"x":0.32,"y":0},"i":{"x":0.67,"y":0},"s":[451,330.5],"t":0},{"o":{"x":0.32,"y":0},"i":{"x":0.67,"y":0},"s":[451,330.5],"t":18.06},{"o":{"x":0.32,"y":0},"i":{"x":0.67,"y":0},"s":[451,330.5],"t":21},{"o":{"x":0.32,"y":0},"i":{"x":0.67,"y":0},"s":[451,330.5],"t":24},{"o":{"x":0.32,"y":0},"i":{"x":0.67,"y":0},"s":[451,330.5],"t":27},{"o":{"x":0.32,"y":0},"i":{"x":0.67,"y":0},"s":[451,330.5],"t":30},{"o":{"x":0.32,"y":0},"i":{"x":0.67,"y":0},"s":[451,330.5],"t":33},{"o":{"x":0.32,"y":0},"i":{"x":0.67,"y":0},"s":[475,441],"t":69},{"s":[475,441],"t":129}]},"r":{"a":1,"k":[{"o":{"x":0.32,"y":0},"i":{"x":0.67,"y":0},"s":[0],"t":0},{"o":{"x":0.32,"y":0},"i":{"x":0.67,"y":0},"s":[0],"t":18.06},{"o":{"x":0.32,"y":0},"i":{"x":0.67,"y":0},"s":[0],"t":21},{"o":{"x":0.32,"y":0},"i":{"x":0.67,"y":0},"s":[0],"t":24},{"o":{"x":0.32,"y":0},"i":{"x":0.67,"y":0},"s":[0],"t":27},{"o":{"x":0.32,"y":0},"i":{"x":0.67,"y":0},"s":[0],"t":30},{"o":{"x":0.32,"y":0},"i":{"x":0.67,"y":0},"s":[0],"t":33},{"o":{"x":0.32,"y":0},"i":{"x":0.67,"y":0},"s":[0],"t":69},{"s":[0],"t":129}]},"sa":{"a":0,"k":0},"o":{"a":1,"k":[{"o":{"x":0.32,"y":0},"i":{"x":0.67,"y":0},"s":[0],"t":0},{"o":{"x":0.32,"y":0},"i":{"x":0.67,"y":0},"s":[0],"t":18.06},{"o":{"x":0.32,"y":0},"i":{"x":0.67,"y":0},"s":[100],"t":21},{"o":{"x":0.32,"y":0},"i":{"x":0.67,"y":0},"s":[100],"t":24},{"o":{"x":0.32,"y":0},"i":{"x":0.67,"y":0},"s":[100],"t":27},{"o":{"x":0.32,"y":0},"i":{"x":0.67,"y":0},"s":[100],"t":30},{"o":{"x":0.32,"y":0},"i":{"x":0.67,"y":0},"s":[100],"t":33},{"o":{"x":0.32,"y":0},"i":{"x":0.67,"y":0},"s":[100],"t":69},{"s":[100],"t":129}]}},"shapes":[{"ty":"sh","bm":0,"hd":false,"nm":"","d":1,"ks":{"a":1,"k":[{"o":{"x":0.32,"y":0},"i":{"x":0.67,"y":0},"s":[{"c":true,"i":[[0,0],[0,0],[2.77,-84.26],[0,0],[-7.55,56.15],[-0.08,-30.83],[0,0],[-6.08,87.74]],"o":[[0,0],[4.02,85.49],[0,0],[0.98,-9.64],[-1.08,30.76],[0,0],[-3.38,-83.77],[0,0]],"v":[[70,0],[0,0],[0,217],[5,217],[16.25,136.26],[15,217],[68.75,217],[70,0]]}],"t":0},{"o":{"x":0.32,"y":0},"i":{"x":0.67,"y":0},"s":[{"c":true,"i":[[0,0],[0,0],[2.77,-84.26],[0,0],[-7.55,56.15],[-0.08,-30.83],[0,0],[-6.08,87.74]],"o":[[0,0],[4.02,85.49],[0,0],[0.98,-9.64],[-1.08,30.76],[0,0],[-3.38,-83.77],[0,0]],"v":[[70,0],[0,0],[0,217],[5,217],[16.25,136.26],[15,217],[68.75,217],[70,0]]}],"t":18.06},{"o":{"x":0.32,"y":0},"i":{"x":0.67,"y":0},"s":[{"c":true,"i":[[0,0],[0,0],[2.77,-84.26],[0,0],[-7.55,56.15],[-0.08,-30.83],[0,0],[-6.08,87.74]],"o":[[0,0],[4.02,85.49],[0,0],[0.98,-9.64],[-1.08,30.76],[0,0],[-3.38,-83.77],[0,0]],"v":[[70,0],[0,0],[0,217],[5,217],[16.25,136.26],[15,217],[68.75,217],[70,0]]}],"t":21},{"o":{"x":0.32,"y":0},"i":{"x":0.67,"y":0},"s":[{"c":true,"i":[[0,0],[0,0],[2.77,-84.26],[0,0],[-7.55,56.15],[-0.08,-30.83],[0,0],[-6.08,87.74]],"o":[[0,0],[4.02,85.49],[0,0],[0.98,-9.64],[-1.08,30.76],[0,0],[-3.38,-83.77],[0,0]],"v":[[70,0],[0,0],[0,217],[5,217],[16.25,136.26],[15,217],[68.75,217],[70,0]]}],"t":24},{"o":{"x":0.32,"y":0},"i":{"x":0.67,"y":0},"s":[{"c":true,"i":[[0,0],[0,0],[2.77,-84.26],[0,0],[-7.55,56.15],[-0.08,-30.83],[0,0],[-6.08,87.74]],"o":[[0,0],[4.02,85.49],[0,0],[0.98,-9.64],[-1.08,30.76],[0,0],[-3.38,-83.77],[0,0]],"v":[[70,0],[0,0],[0,217],[5,217],[16.25,136.26],[15,217],[68.75,217],[70,0]]}],"t":27},{"o":{"x":0.32,"y":0},"i":{"x":0.67,"y":0},"s":[{"c":true,"i":[[0,0],[0,0],[2.77,-84.26],[0,0],[-7.55,56.15],[-0.08,-30.83],[0,0],[-6.08,87.74]],"o":[[0,0],[4.02,85.49],[0,0],[0.98,-9.64],[-1.08,30.76],[0,0],[-3.38,-83.77],[0,0]],"v":[[70,0],[0,0],[0,217],[5,217],[16.25,136.26],[15,217],[68.75,217],[70,0]]}],"t":30},{"o":{"x":0.32,"y":0},"i":{"x":0.67,"y":0},"s":[{"c":true,"i":[[0,0],[0,0],[2.77,-84.26],[0,0],[-7.55,56.15],[-0.08,-30.83],[0,0],[-6.08,87.74]],"o":[[0,0],[4.02,85.49],[0,0],[0.98,-9.64],[-1.08,30.76],[0,0],[-3.38,-83.77],[0,0]],"v":[[70,0],[0,0],[0,217],[5,217],[16.25,136.26],[15,217],[68.75,217],[70,0]]}],"t":33},{"o":{"x":0.32,"y":0},"i":{"x":0.67,"y":0},"s":[{"c":true,"i":[[0,0],[0,0],[1.59,-48.15],[0,0],[-4.31,32.09],[-0.04,-17.62],[0,0],[-3.47,50.14]],"o":[[0,0],[2.3,48.85],[0,0],[0.56,-5.51],[-0.62,17.58],[0,0],[-1.93,-47.87],[0,0]],"v":[[40,0],[0,0],[0,124],[2.86,124],[9.29,77.86],[8.57,124],[39.29,124],[40,0]]}],"t":69},{"s":[{"c":true,"i":[[0,0],[0,0],[1.59,-48.15],[0,0],[-4.31,32.09],[-0.04,-17.62],[0,0],[-3.47,50.14]],"o":[[0,0],[2.3,48.85],[0,0],[0.56,-5.51],[-0.62,17.58],[0,0],[-1.93,-47.87],[0,0]],"v":[[40,0],[0,0],[0,124],[2.86,124],[9.29,77.86],[8.57,124],[39.29,124],[40,0]]}],"t":129}]}},{"ty":"fl","bm":0,"hd":false,"nm":"","c":{"a":1,"k":[{"o":{"x":0.32,"y":0},"i":{"x":0.67,"y":0},"s":[0.2902,0.6,0.3765],"t":0},{"o":{"x":0.32,"y":0},"i":{"x":0.67,"y":0},"s":[0.2902,0.6,0.3765],"t":18.06},{"o":{"x":0.32,"y":0},"i":{"x":0.67,"y":0},"s":[0.2902,0.6,0.3765],"t":21},{"o":{"x":0.32,"y":0},"i":{"x":0.67,"y":0},"s":[0.2902,0.6,0.3765],"t":24},{"o":{"x":0.32,"y":0},"i":{"x":0.67,"y":0},"s":[0.2902,0.6,0.3765],"t":27},{"o":{"x":0.32,"y":0},"i":{"x":0.67,"y":0},"s":[0.2902,0.6,0.3765],"t":30},{"o":{"x":0.32,"y":0},"i":{"x":0.67,"y":0},"s":[0.2902,0.6,0.3765],"t":33},{"o":{"x":0.32,"y":0},"i":{"x":0.67,"y":0},"s":[0.2902,0.6,0.3765],"t":69},{"s":[0.2902,0.6,0.3765],"t":129}]},"r":1,"o":{"a":1,"k":[{"o":{"x":0.32,"y":0},"i":{"x":0.67,"y":0},"s":[100],"t":0},{"o":{"x":0.32,"y":0},"i":{"x":0.67,"y":0},"s":[100],"t":18.06},{"o":{"x":0.32,"y":0},"i":{"x":0.67,"y":0},"s":[100],"t":21},{"o":{"x":0.32,"y":0},"i":{"x":0.67,"y":0},"s":[100],"t":24},{"o":{"x":0.32,"y":0},"i":{"x":0.67,"y":0},"s":[100],"t":27},{"o":{"x":0.32,"y":0},"i":{"x":0.67,"y":0},"s":[100],"t":30},{"o":{"x":0.32,"y":0},"i":{"x":0.67,"y":0},"s":[100],"t":33},{"o":{"x":0.32,"y":0},"i":{"x":0.67,"y":0},"s":[100],"t":69},{"s":[100],"t":129}]}}],"ind":3},{"ty":4,"nm":"Vector 31","sr":1,"st":0,"op":130.06,"ip":0,"hd":false,"ddd":0,"bm":0,"hasMask":false,"ao":0,"ks":{"a":{"a":1,"k":[{"o":{"x":0.32,"y":0},"i":{"x":0.67,"y":0},"s":[34,108.5],"t":0},{"o":{"x":0.32,"y":0},"i":{"x":0.67,"y":0},"s":[34,108.5],"t":0.06},{"o":{"x":0.32,"y":0},"i":{"x":0.67,"y":0},"s":[34,108.5],"t":12},{"o":{"x":0.32,"y":0},"i":{"x":0.67,"y":0},"s":[34,108.5],"t":18},{"o":{"x":0.32,"y":0},"i":{"x":0.67,"y":0},"s":[34,108.5],"t":21},{"o":{"x":0.32,"y":0},"i":{"x":0.67,"y":0},"s":[34,108.5],"t":24},{"o":{"x":0.32,"y":0},"i":{"x":0.67,"y":0},"s":[34,108.5],"t":27},{"o":{"x":0.32,"y":0},"i":{"x":0.67,"y":0},"s":[34,108.5],"t":30},{"o":{"x":0.32,"y":0},"i":{"x":0.67,"y":0},"s":[34,108.5],"t":33},{"o":{"x":0.32,"y":0},"i":{"x":0.67,"y":0},"s":[19.5,62],"t":69},{"s":[19.5,62],"t":129}]},"s":{"a":1,"k":[{"o":{"x":0.32,"y":0},"i":{"x":0.67,"y":0},"s":[100,100],"t":0},{"o":{"x":0.32,"y":0},"i":{"x":0.67,"y":0},"s":[100,100],"t":0.06},{"o":{"x":0.32,"y":0},"i":{"x":0.67,"y":0},"s":[100,100],"t":12},{"o":{"x":0.32,"y":0},"i":{"x":0.67,"y":0},"s":[100,100],"t":18},{"o":{"x":0.32,"y":0},"i":{"x":0.67,"y":0},"s":[100,100],"t":21},{"o":{"x":0.32,"y":0},"i":{"x":0.67,"y":0},"s":[100,100],"t":24},{"o":{"x":0.32,"y":0},"i":{"x":0.67,"y":0},"s":[100,100],"t":27},{"o":{"x":0.32,"y":0},"i":{"x":0.67,"y":0},"s":[100,100],"t":30},{"o":{"x":0.32,"y":0},"i":{"x":0.67,"y":0},"s":[100,100],"t":33},{"o":{"x":0.32,"y":0},"i":{"x":0.67,"y":0},"s":[100,100],"t":69},{"s":[100,100],"t":129}]},"sk":{"a":0,"k":0},"p":{"a":1,"k":[{"o":{"x":0.32,"y":0},"i":{"x":0.67,"y":0},"s":[450,778.5],"t":0},{"o":{"x":0.32,"y":0},"i":{"x":0.67,"y":0},"s":[450,778.5],"t":0.06},{"o":{"x":0.32,"y":0},"i":{"x":0.67,"y":0},"s":[450,778.5],"t":12},{"o":{"x":0.32,"y":0},"i":{"x":0.67,"y":0},"s":[450,778.5],"t":18},{"o":{"x":0.32,"y":0},"i":{"x":0.67,"y":0},"s":[450,778.5],"t":21},{"o":{"x":0.32,"y":0},"i":{"x":0.67,"y":0},"s":[450,778.5],"t":24},{"o":{"x":0.32,"y":0},"i":{"x":0.67,"y":0},"s":[450,778.5],"t":27},{"o":{"x":0.32,"y":0},"i":{"x":0.67,"y":0},"s":[450,778.5],"t":30},{"o":{"x":0.32,"y":0},"i":{"x":0.67,"y":0},"s":[450,778.5],"t":33},{"o":{"x":0.32,"y":0},"i":{"x":0.67,"y":0},"s":[474.5,698],"t":69},{"s":[474.5,698],"t":129}]},"r":{"a":1,"k":[{"o":{"x":0.32,"y":0},"i":{"x":0.67,"y":0},"s":[0],"t":0},{"o":{"x":0.32,"y":0},"i":{"x":0.67,"y":0},"s":[0],"t":0.06},{"o":{"x":0.32,"y":0},"i":{"x":0.67,"y":0},"s":[0],"t":12},{"o":{"x":0.32,"y":0},"i":{"x":0.67,"y":0},"s":[0],"t":18},{"o":{"x":0.32,"y":0},"i":{"x":0.67,"y":0},"s":[0],"t":21},{"o":{"x":0.32,"y":0},"i":{"x":0.67,"y":0},"s":[0],"t":24},{"o":{"x":0.32,"y":0},"i":{"x":0.67,"y":0},"s":[0],"t":27},{"o":{"x":0.32,"y":0},"i":{"x":0.67,"y":0},"s":[0],"t":30},{"o":{"x":0.32,"y":0},"i":{"x":0.67,"y":0},"s":[0],"t":33},{"o":{"x":0.32,"y":0},"i":{"x":0.67,"y":0},"s":[0],"t":69},{"s":[0],"t":129}]},"sa":{"a":0,"k":0},"o":{"a":1,"k":[{"o":{"x":0.32,"y":0},"i":{"x":0.67,"y":0},"s":[0],"t":0},{"o":{"x":0.32,"y":0},"i":{"x":0.67,"y":0},"s":[0],"t":0.06},{"o":{"x":0.32,"y":0},"i":{"x":0.67,"y":0},"s":[100],"t":12},{"o":{"x":0.32,"y":0},"i":{"x":0.67,"y":0},"s":[100],"t":18},{"o":{"x":0.32,"y":0},"i":{"x":0.67,"y":0},"s":[100],"t":21},{"o":{"x":0.32,"y":0},"i":{"x":0.67,"y":0},"s":[100],"t":24},{"o":{"x":0.32,"y":0},"i":{"x":0.67,"y":0},"s":[100],"t":27},{"o":{"x":0.32,"y":0},"i":{"x":0.67,"y":0},"s":[100],"t":30},{"o":{"x":0.32,"y":0},"i":{"x":0.67,"y":0},"s":[100],"t":33},{"o":{"x":0.32,"y":0},"i":{"x":0.67,"y":0},"s":[100],"t":69},{"s":[100],"t":129}]}},"shapes":[{"ty":"sh","bm":0,"hd":false,"nm":"","d":1,"ks":{"a":1,"k":[{"o":{"x":0.32,"y":0},"i":{"x":0.67,"y":0},"s":[{"c":true,"i":[[0,0],[-4.78,89.64],[0,0],[3.66,-84.29],[0,0],[-4.98,34.64],[-0.62,-29.32],[0,0],[0,0]],"o":[[-2.99,-79.78],[0,0],[3.09,85.1],[0,0],[2.46,-25.52],[-0.73,30.9],[0,0],[0,0],[0,0]],"v":[[67.92,214.87],[68,0],[0,0],[0,217],[6.18,217],[16.07,138.68],[16.07,217],[68,217],[67.92,214.87]]}],"t":0},{"o":{"x":0.32,"y":0},"i":{"x":0.67,"y":0},"s":[{"c":true,"i":[[0,0],[-4.78,89.64],[0,0],[3.66,-84.29],[0,0],[-4.98,34.64],[-0.62,-29.32],[0,0],[0,0]],"o":[[-2.99,-79.78],[0,0],[3.09,85.1],[0,0],[2.46,-25.52],[-0.73,30.9],[0,0],[0,0],[0,0]],"v":[[67.92,214.87],[68,0],[0,0],[0,217],[6.18,217],[16.07,138.68],[16.07,217],[68,217],[67.92,214.87]]}],"t":0.06},{"o":{"x":0.32,"y":0},"i":{"x":0.67,"y":0},"s":[{"c":true,"i":[[0,0],[-4.78,89.64],[0,0],[3.66,-84.29],[0,0],[-4.98,34.64],[-0.62,-29.32],[0,0],[0,0]],"o":[[-2.99,-79.78],[0,0],[3.09,85.1],[0,0],[2.46,-25.52],[-0.73,30.9],[0,0],[0,0],[0,0]],"v":[[67.92,214.87],[68,0],[0,0],[0,217],[6.18,217],[16.07,138.68],[16.07,217],[68,217],[67.92,214.87]]}],"t":12},{"o":{"x":0.32,"y":0},"i":{"x":0.67,"y":0},"s":[{"c":true,"i":[[0,0],[-4.78,89.64],[0,0],[3.66,-84.29],[0,0],[-4.98,34.64],[-0.62,-29.32],[0,0],[0,0]],"o":[[-2.99,-79.78],[0,0],[3.09,85.1],[0,0],[2.46,-25.52],[-0.73,30.9],[0,0],[0,0],[0,0]],"v":[[67.92,214.87],[68,0],[0,0],[0,217],[6.18,217],[16.07,138.68],[16.07,217],[68,217],[67.92,214.87]]}],"t":18},{"o":{"x":0.32,"y":0},"i":{"x":0.67,"y":0},"s":[{"c":true,"i":[[0,0],[-4.78,89.64],[0,0],[3.66,-84.29],[0,0],[-4.98,34.64],[-0.62,-29.32],[0,0],[0,0]],"o":[[-2.99,-79.78],[0,0],[3.09,85.1],[0,0],[2.46,-25.52],[-0.73,30.9],[0,0],[0,0],[0,0]],"v":[[67.92,214.87],[68,0],[0,0],[0,217],[6.18,217],[16.07,138.68],[16.07,217],[68,217],[67.92,214.87]]}],"t":21},{"o":{"x":0.32,"y":0},"i":{"x":0.67,"y":0},"s":[{"c":true,"i":[[0,0],[-4.78,89.64],[0,0],[3.66,-84.29],[0,0],[-4.98,34.64],[-0.62,-29.32],[0,0],[0,0]],"o":[[-2.99,-79.78],[0,0],[3.09,85.1],[0,0],[2.46,-25.52],[-0.73,30.9],[0,0],[0,0],[0,0]],"v":[[67.92,214.87],[68,0],[0,0],[0,217],[6.18,217],[16.07,138.68],[16.07,217],[68,217],[67.92,214.87]]}],"t":24},{"o":{"x":0.32,"y":0},"i":{"x":0.67,"y":0},"s":[{"c":true,"i":[[0,0],[-4.78,89.64],[0,0],[3.66,-84.29],[0,0],[-4.98,34.64],[-0.62,-29.32],[0,0],[0,0]],"o":[[-2.99,-79.78],[0,0],[3.09,85.1],[0,0],[2.46,-25.52],[-0.73,30.9],[0,0],[0,0],[0,0]],"v":[[67.92,214.87],[68,0],[0,0],[0,217],[6.18,217],[16.07,138.68],[16.07,217],[68,217],[67.92,214.87]]}],"t":27},{"o":{"x":0.32,"y":0},"i":{"x":0.67,"y":0},"s":[{"c":true,"i":[[0,0],[-4.78,89.64],[0,0],[3.66,-84.29],[0,0],[-4.98,34.64],[-0.62,-29.32],[0,0],[0,0]],"o":[[-2.99,-79.78],[0,0],[3.09,85.1],[0,0],[2.46,-25.52],[-0.73,30.9],[0,0],[0,0],[0,0]],"v":[[67.92,214.87],[68,0],[0,0],[0,217],[6.18,217],[16.07,138.68],[16.07,217],[68,217],[67.92,214.87]]}],"t":30},{"o":{"x":0.32,"y":0},"i":{"x":0.67,"y":0},"s":[{"c":true,"i":[[0,0],[-4.78,89.64],[0,0],[3.66,-84.29],[0,0],[-4.98,34.64],[-0.62,-29.32],[0,0],[0,0]],"o":[[-2.99,-79.78],[0,0],[3.09,85.1],[0,0],[2.46,-25.52],[-0.73,30.9],[0,0],[0,0],[0,0]],"v":[[67.92,214.87],[68,0],[0,0],[0,217],[6.18,217],[16.07,138.68],[16.07,217],[68,217],[67.92,214.87]]}],"t":33},{"o":{"x":0.32,"y":0},"i":{"x":0.67,"y":0},"s":[{"c":true,"i":[[0,0],[-2.74,51.22],[0,0],[2.1,-48.16],[0,0],[-2.86,19.79],[-0.35,-16.76],[0,0],[0,0]],"o":[[-1.72,-45.59],[0,0],[1.77,48.63],[0,0],[1.41,-14.58],[-0.42,17.66],[0,0],[0,0],[0,0]],"v":[[38.95,122.78],[39,0],[0,0],[0,124],[3.55,124],[9.22,79.24],[9.22,124],[39,124],[38.95,122.78]]}],"t":69},{"s":[{"c":true,"i":[[0,0],[-2.74,51.22],[0,0],[2.1,-48.16],[0,0],[-2.86,19.79],[-0.35,-16.76],[0,0],[0,0]],"o":[[-1.72,-45.59],[0,0],[1.77,48.63],[0,0],[1.41,-14.58],[-0.42,17.66],[0,0],[0,0],[0,0]],"v":[[38.95,122.78],[39,0],[0,0],[0,124],[3.55,124],[9.22,79.24],[9.22,124],[39,124],[38.95,122.78]]}],"t":129}]}},{"ty":"fl","bm":0,"hd":false,"nm":"","c":{"a":1,"k":[{"o":{"x":0.32,"y":0},"i":{"x":0.67,"y":0},"s":[0.2902,0.6,0.3765],"t":0},{"o":{"x":0.32,"y":0},"i":{"x":0.67,"y":0},"s":[0.2902,0.6,0.3765],"t":0.06},{"o":{"x":0.32,"y":0},"i":{"x":0.67,"y":0},"s":[0.2902,0.6,0.3765],"t":12},{"o":{"x":0.32,"y":0},"i":{"x":0.67,"y":0},"s":[0.2902,0.6,0.3765],"t":18},{"o":{"x":0.32,"y":0},"i":{"x":0.67,"y":0},"s":[0.2902,0.6,0.3765],"t":21},{"o":{"x":0.32,"y":0},"i":{"x":0.67,"y":0},"s":[0.2902,0.6,0.3765],"t":24},{"o":{"x":0.32,"y":0},"i":{"x":0.67,"y":0},"s":[0.2902,0.6,0.3765],"t":27},{"o":{"x":0.32,"y":0},"i":{"x":0.67,"y":0},"s":[0.2902,0.6,0.3765],"t":30},{"o":{"x":0.32,"y":0},"i":{"x":0.67,"y":0},"s":[0.2902,0.6,0.3765],"t":33},{"o":{"x":0.32,"y":0},"i":{"x":0.67,"y":0},"s":[0.2902,0.6,0.3765],"t":69},{"s":[0.2902,0.6,0.3765],"t":129}]},"r":1,"o":{"a":1,"k":[{"o":{"x":0.32,"y":0},"i":{"x":0.67,"y":0},"s":[100],"t":0},{"o":{"x":0.32,"y":0},"i":{"x":0.67,"y":0},"s":[100],"t":0.06},{"o":{"x":0.32,"y":0},"i":{"x":0.67,"y":0},"s":[100],"t":12},{"o":{"x":0.32,"y":0},"i":{"x":0.67,"y":0},"s":[100],"t":18},{"o":{"x":0.32,"y":0},"i":{"x":0.67,"y":0},"s":[100],"t":21},{"o":{"x":0.32,"y":0},"i":{"x":0.67,"y":0},"s":[100],"t":24},{"o":{"x":0.32,"y":0},"i":{"x":0.67,"y":0},"s":[100],"t":27},{"o":{"x":0.32,"y":0},"i":{"x":0.67,"y":0},"s":[100],"t":30},{"o":{"x":0.32,"y":0},"i":{"x":0.67,"y":0},"s":[100],"t":33},{"o":{"x":0.32,"y":0},"i":{"x":0.67,"y":0},"s":[100],"t":69},{"s":[100],"t":129}]}}],"ind":4},{"ty":4,"nm":"Vector 38","sr":1,"st":0,"op":130.06,"ip":0,"hd":false,"ddd":0,"bm":0,"hasMask":false,"ao":0,"ks":{"a":{"a":1,"k":[{"o":{"x":0.32,"y":0},"i":{"x":0.67,"y":0},"s":[8,37.5],"t":0},{"o":{"x":0.32,"y":0},"i":{"x":0.67,"y":0},"s":[8,37.5],"t":24.06},{"o":{"x":0.32,"y":0},"i":{"x":0.67,"y":0},"s":[8,37.5],"t":27},{"o":{"x":0.32,"y":0},"i":{"x":0.67,"y":0},"s":[8,37.5],"t":30},{"o":{"x":0.32,"y":0},"i":{"x":0.67,"y":0},"s":[8,37.5],"t":33},{"o":{"x":0.32,"y":0},"i":{"x":0.67,"y":0},"s":[4.5,21.5],"t":69},{"s":[4.5,21.5],"t":129}]},"s":{"a":1,"k":[{"o":{"x":0.32,"y":0},"i":{"x":0.67,"y":0},"s":[100,100],"t":0},{"o":{"x":0.32,"y":0},"i":{"x":0.67,"y":0},"s":[100,100],"t":24.06},{"o":{"x":0.32,"y":0},"i":{"x":0.67,"y":0},"s":[100,100],"t":27},{"o":{"x":0.32,"y":0},"i":{"x":0.67,"y":0},"s":[100,100],"t":30},{"o":{"x":0.32,"y":0},"i":{"x":0.67,"y":0},"s":[100,100],"t":33},{"o":{"x":0.32,"y":0},"i":{"x":0.67,"y":0},"s":[100,100],"t":69},{"s":[100,100],"t":129}]},"sk":{"a":0,"k":0},"p":{"a":1,"k":[{"o":{"x":0.32,"y":0},"i":{"x":0.67,"y":0},"s":[511,816.5],"t":0},{"o":{"x":0.32,"y":0},"i":{"x":0.67,"y":0},"s":[511,816.5],"t":24.06},{"o":{"x":0.32,"y":0},"i":{"x":0.67,"y":0},"s":[511,816.5],"t":27},{"o":{"x":0.32,"y":0},"i":{"x":0.67,"y":0},"s":[511,816.5],"t":30},{"o":{"x":0.32,"y":0},"i":{"x":0.67,"y":0},"s":[511,816.5],"t":33},{"o":{"x":0.32,"y":0},"i":{"x":0.67,"y":0},"s":[509.5,719.5],"t":69},{"s":[509.5,719.5],"t":129}]},"r":{"a":1,"k":[{"o":{"x":0.32,"y":0},"i":{"x":0.67,"y":0},"s":[0],"t":0},{"o":{"x":0.32,"y":0},"i":{"x":0.67,"y":0},"s":[0],"t":24.06},{"o":{"x":0.32,"y":0},"i":{"x":0.67,"y":0},"s":[0],"t":27},{"o":{"x":0.32,"y":0},"i":{"x":0.67,"y":0},"s":[0],"t":30},{"o":{"x":0.32,"y":0},"i":{"x":0.67,"y":0},"s":[0],"t":33},{"o":{"x":0.32,"y":0},"i":{"x":0.67,"y":0},"s":[0],"t":69},{"s":[0],"t":129}]},"sa":{"a":0,"k":0},"o":{"a":1,"k":[{"o":{"x":0.32,"y":0},"i":{"x":0.67,"y":0},"s":[0],"t":0},{"o":{"x":0.32,"y":0},"i":{"x":0.67,"y":0},"s":[0],"t":24.06},{"o":{"x":0.32,"y":0},"i":{"x":0.67,"y":0},"s":[100],"t":27},{"o":{"x":0.32,"y":0},"i":{"x":0.67,"y":0},"s":[100],"t":30},{"o":{"x":0.32,"y":0},"i":{"x":0.67,"y":0},"s":[100],"t":33},{"o":{"x":0.32,"y":0},"i":{"x":0.67,"y":0},"s":[100],"t":69},{"s":[100],"t":129}]}},"shapes":[{"ty":"sh","bm":0,"hd":false,"nm":"","d":1,"ks":{"a":1,"k":[{"o":{"x":0.32,"y":0},"i":{"x":0.67,"y":0},"s":[{"c":true,"i":[[0,0],[0,0],[-6.64,31.1],[-1.04,-28.76]],"o":[[0,0],[4.35,-20.53],[-0.91,29.83],[0,0]],"v":[[16,75],[0,75],[16,0],[16,75]]}],"t":0},{"o":{"x":0.32,"y":0},"i":{"x":0.67,"y":0},"s":[{"c":true,"i":[[0,0],[0,0],[-6.64,31.1],[-1.04,-28.76]],"o":[[0,0],[4.35,-20.53],[-0.91,29.83],[0,0]],"v":[[16,75],[0,75],[16,0],[16,75]]}],"t":24.06},{"o":{"x":0.32,"y":0},"i":{"x":0.67,"y":0},"s":[{"c":true,"i":[[0,0],[0,0],[-6.64,31.1],[-1.04,-28.76]],"o":[[0,0],[4.35,-20.53],[-0.91,29.83],[0,0]],"v":[[16,75],[0,75],[16,0],[16,75]]}],"t":27},{"o":{"x":0.32,"y":0},"i":{"x":0.67,"y":0},"s":[{"c":true,"i":[[0,0],[0,0],[-6.64,31.1],[-1.04,-28.76]],"o":[[0,0],[4.35,-20.53],[-0.91,29.83],[0,0]],"v":[[16,75],[0,75],[16,0],[16,75]]}],"t":30},{"o":{"x":0.32,"y":0},"i":{"x":0.67,"y":0},"s":[{"c":true,"i":[[0,0],[0,0],[-6.64,31.1],[-1.04,-28.76]],"o":[[0,0],[4.35,-20.53],[-0.91,29.83],[0,0]],"v":[[16,75],[0,75],[16,0],[16,75]]}],"t":33},{"o":{"x":0.32,"y":0},"i":{"x":0.67,"y":0},"s":[{"c":true,"i":[[0,0],[0,0],[-3.74,17.83],[-0.59,-16.49]],"o":[[0,0],[2.45,-11.77],[-0.51,17.1],[0,0]],"v":[[9,43],[0,43],[9,0],[9,43]]}],"t":69},{"s":[{"c":true,"i":[[0,0],[0,0],[-3.74,17.83],[-0.59,-16.49]],"o":[[0,0],[2.45,-11.77],[-0.51,17.1],[0,0]],"v":[[9,43],[0,43],[9,0],[9,43]]}],"t":129}]}},{"ty":"fl","bm":0,"hd":false,"nm":"","c":{"a":1,"k":[{"o":{"x":0.32,"y":0},"i":{"x":0.67,"y":0},"s":[1,1,1],"t":0},{"o":{"x":0.32,"y":0},"i":{"x":0.67,"y":0},"s":[1,1,1],"t":24.06},{"o":{"x":0.32,"y":0},"i":{"x":0.67,"y":0},"s":[1,1,1],"t":27},{"o":{"x":0.32,"y":0},"i":{"x":0.67,"y":0},"s":[1,1,1],"t":30},{"o":{"x":0.32,"y":0},"i":{"x":0.67,"y":0},"s":[1,1,1],"t":33},{"o":{"x":0.32,"y":0},"i":{"x":0.67,"y":0},"s":[1,1,1],"t":69},{"s":[1,1,1],"t":129}]},"r":1,"o":{"a":1,"k":[{"o":{"x":0.32,"y":0},"i":{"x":0.67,"y":0},"s":[100],"t":0},{"o":{"x":0.32,"y":0},"i":{"x":0.67,"y":0},"s":[100],"t":24.06},{"o":{"x":0.32,"y":0},"i":{"x":0.67,"y":0},"s":[100],"t":27},{"o":{"x":0.32,"y":0},"i":{"x":0.67,"y":0},"s":[100],"t":30},{"o":{"x":0.32,"y":0},"i":{"x":0.67,"y":0},"s":[100],"t":33},{"o":{"x":0.32,"y":0},"i":{"x":0.67,"y":0},"s":[100],"t":69},{"s":[100],"t":129}]}}],"ind":5},{"ty":4,"nm":"Vector 37","sr":1,"st":0,"op":130.06,"ip":0,"hd":false,"ddd":0,"bm":0,"hasMask":false,"ao":0,"ks":{"a":{"a":1,"k":[{"o":{"x":0.32,"y":0},"i":{"x":0.67,"y":0},"s":[24,78.5],"t":0},{"o":{"x":0.32,"y":0},"i":{"x":0.67,"y":0},"s":[24,78.5],"t":24.06},{"o":{"x":0.32,"y":0},"i":{"x":0.67,"y":0},"s":[24,78.5],"t":27},{"o":{"x":0.32,"y":0},"i":{"x":0.67,"y":0},"s":[24,78.5],"t":30},{"o":{"x":0.32,"y":0},"i":{"x":0.67,"y":0},"s":[24,78.5],"t":33},{"o":{"x":0.32,"y":0},"i":{"x":0.67,"y":0},"s":[13.5,45],"t":69},{"s":[13.5,45],"t":129}]},"s":{"a":1,"k":[{"o":{"x":0.32,"y":0},"i":{"x":0.67,"y":0},"s":[100,100],"t":0},{"o":{"x":0.32,"y":0},"i":{"x":0.67,"y":0},"s":[100,100],"t":24.06},{"o":{"x":0.32,"y":0},"i":{"x":0.67,"y":0},"s":[100,100],"t":27},{"o":{"x":0.32,"y":0},"i":{"x":0.67,"y":0},"s":[100,100],"t":30},{"o":{"x":0.32,"y":0},"i":{"x":0.67,"y":0},"s":[100,100],"t":33},{"o":{"x":0.32,"y":0},"i":{"x":0.67,"y":0},"s":[100,100],"t":69},{"s":[100,100],"t":129}]},"sk":{"a":0,"k":0},"p":{"a":1,"k":[{"o":{"x":0.32,"y":0},"i":{"x":0.67,"y":0},"s":[517,808.5],"t":0},{"o":{"x":0.32,"y":0},"i":{"x":0.67,"y":0},"s":[517,808.5],"t":24.06},{"o":{"x":0.32,"y":0},"i":{"x":0.67,"y":0},"s":[517,808.5],"t":27},{"o":{"x":0.32,"y":0},"i":{"x":0.67,"y":0},"s":[517,808.5],"t":30},{"o":{"x":0.32,"y":0},"i":{"x":0.67,"y":0},"s":[517,808.5],"t":33},{"o":{"x":0.32,"y":0},"i":{"x":0.67,"y":0},"s":[512.5,715],"t":69},{"s":[512.5,715],"t":129}]},"r":{"a":1,"k":[{"o":{"x":0.32,"y":0},"i":{"x":0.67,"y":0},"s":[0],"t":0},{"o":{"x":0.32,"y":0},"i":{"x":0.67,"y":0},"s":[0],"t":24.06},{"o":{"x":0.32,"y":0},"i":{"x":0.67,"y":0},"s":[0],"t":27},{"o":{"x":0.32,"y":0},"i":{"x":0.67,"y":0},"s":[0],"t":30},{"o":{"x":0.32,"y":0},"i":{"x":0.67,"y":0},"s":[0],"t":33},{"o":{"x":0.32,"y":0},"i":{"x":0.67,"y":0},"s":[0],"t":69},{"s":[0],"t":129}]},"sa":{"a":0,"k":0},"o":{"a":1,"k":[{"o":{"x":0.32,"y":0},"i":{"x":0.67,"y":0},"s":[0],"t":0},{"o":{"x":0.32,"y":0},"i":{"x":0.67,"y":0},"s":[0],"t":24.06},{"o":{"x":0.32,"y":0},"i":{"x":0.67,"y":0},"s":[100],"t":27},{"o":{"x":0.32,"y":0},"i":{"x":0.67,"y":0},"s":[100],"t":30},{"o":{"x":0.32,"y":0},"i":{"x":0.67,"y":0},"s":[100],"t":33},{"o":{"x":0.32,"y":0},"i":{"x":0.67,"y":0},"s":[100],"t":69},{"s":[100],"t":129}]}},"shapes":[{"ty":"sh","bm":0,"hd":false,"nm":"","d":1,"ks":{"a":1,"k":[{"o":{"x":0.32,"y":0},"i":{"x":0.67,"y":0},"s":[{"c":true,"i":[[0,0],[0,0],[-3.44,-49.83],[0,0],[-6.29,74.11]],"o":[[0,0],[-0.1,70.12],[0,0],[-8.28,-46.16],[0,0]],"v":[[45.54,3.89],[0.02,0],[3.71,157],[48,157],[45.54,3.89]]}],"t":0},{"o":{"x":0.32,"y":0},"i":{"x":0.67,"y":0},"s":[{"c":true,"i":[[0,0],[0,0],[-3.44,-49.83],[0,0],[-6.29,74.11]],"o":[[0,0],[-0.1,70.12],[0,0],[-8.28,-46.16],[0,0]],"v":[[45.54,3.89],[0.02,0],[3.71,157],[48,157],[45.54,3.89]]}],"t":24.06},{"o":{"x":0.32,"y":0},"i":{"x":0.67,"y":0},"s":[{"c":true,"i":[[0,0],[0,0],[-3.44,-49.83],[0,0],[-6.29,74.11]],"o":[[0,0],[-0.1,70.12],[0,0],[-8.28,-46.16],[0,0]],"v":[[45.54,3.89],[0.02,0],[3.71,157],[48,157],[45.54,3.89]]}],"t":27},{"o":{"x":0.32,"y":0},"i":{"x":0.67,"y":0},"s":[{"c":true,"i":[[0,0],[0,0],[-3.44,-49.83],[0,0],[-6.29,74.11]],"o":[[0,0],[-0.1,70.12],[0,0],[-8.28,-46.16],[0,0]],"v":[[45.54,3.89],[0.02,0],[3.71,157],[48,157],[45.54,3.89]]}],"t":30},{"o":{"x":0.32,"y":0},"i":{"x":0.67,"y":0},"s":[{"c":true,"i":[[0,0],[0,0],[-3.44,-49.83],[0,0],[-6.29,74.11]],"o":[[0,0],[-0.1,70.12],[0,0],[-8.28,-46.16],[0,0]],"v":[[45.54,3.89],[0.02,0],[3.71,157],[48,157],[45.54,3.89]]}],"t":33},{"o":{"x":0.32,"y":0},"i":{"x":0.67,"y":0},"s":[{"c":true,"i":[[0,0],[0,0],[-1.93,-28.56],[0,0],[-3.54,42.48]],"o":[[0,0],[-0.06,40.19],[0,0],[-4.66,-26.46],[0,0]],"v":[[25.62,2.23],[0.01,0],[2.08,90],[27,90],[25.62,2.23]]}],"t":69},{"s":[{"c":true,"i":[[0,0],[0,0],[-1.93,-28.56],[0,0],[-3.54,42.48]],"o":[[0,0],[-0.06,40.19],[0,0],[-4.66,-26.46],[0,0]],"v":[[25.62,2.23],[0.01,0],[2.08,90],[27,90],[25.62,2.23]]}],"t":129}]}},{"ty":"fl","bm":0,"hd":false,"nm":"","c":{"a":1,"k":[{"o":{"x":0.32,"y":0},"i":{"x":0.67,"y":0},"s":[0.2902,0.6,0.3765],"t":0},{"o":{"x":0.32,"y":0},"i":{"x":0.67,"y":0},"s":[0.2902,0.6,0.3765],"t":24.06},{"o":{"x":0.32,"y":0},"i":{"x":0.67,"y":0},"s":[0.2902,0.6,0.3765],"t":27},{"o":{"x":0.32,"y":0},"i":{"x":0.67,"y":0},"s":[0.2902,0.6,0.3765],"t":30},{"o":{"x":0.32,"y":0},"i":{"x":0.67,"y":0},"s":[0.2902,0.6,0.3765],"t":33},{"o":{"x":0.32,"y":0},"i":{"x":0.67,"y":0},"s":[0.2902,0.6,0.3765],"t":69},{"s":[0.2902,0.6,0.3765],"t":129}]},"r":1,"o":{"a":1,"k":[{"o":{"x":0.32,"y":0},"i":{"x":0.67,"y":0},"s":[100],"t":0},{"o":{"x":0.32,"y":0},"i":{"x":0.67,"y":0},"s":[100],"t":24.06},{"o":{"x":0.32,"y":0},"i":{"x":0.67,"y":0},"s":[100],"t":27},{"o":{"x":0.32,"y":0},"i":{"x":0.67,"y":0},"s":[100],"t":30},{"o":{"x":0.32,"y":0},"i":{"x":0.67,"y":0},"s":[100],"t":33},{"o":{"x":0.32,"y":0},"i":{"x":0.67,"y":0},"s":[100],"t":69},{"s":[100],"t":129}]}}],"ind":6},{"ty":4,"nm":"Vector 42","sr":1,"st":0,"op":130.06,"ip":0,"hd":false,"ddd":0,"bm":0,"hasMask":false,"ao":0,"ks":{"a":{"a":1,"k":[{"o":{"x":0.32,"y":0},"i":{"x":0.67,"y":0},"s":[64.5,25.5],"t":0},{"o":{"x":0.32,"y":0},"i":{"x":0.67,"y":0},"s":[64.5,25.5],"t":30.06},{"o":{"x":0.32,"y":0},"i":{"x":0.67,"y":0},"s":[64.5,25.5],"t":33},{"o":{"x":0.32,"y":0},"i":{"x":0.67,"y":0},"s":[37,15],"t":69},{"s":[37,15],"t":129}]},"s":{"a":1,"k":[{"o":{"x":0.32,"y":0},"i":{"x":0.67,"y":0},"s":[100,100],"t":0},{"o":{"x":0.32,"y":0},"i":{"x":0.67,"y":0},"s":[100,100],"t":30.06},{"o":{"x":0.32,"y":0},"i":{"x":0.67,"y":0},"s":[100,100],"t":33},{"o":{"x":0.32,"y":0},"i":{"x":0.67,"y":0},"s":[100,100],"t":69},{"s":[100,100],"t":129}]},"sk":{"a":0,"k":0},"p":{"a":1,"k":[{"o":{"x":0.32,"y":0},"i":{"x":0.67,"y":0},"s":[629.5,717.5],"t":0},{"o":{"x":0.32,"y":0},"i":{"x":0.67,"y":0},"s":[629.5,717.5],"t":30.06},{"o":{"x":0.32,"y":0},"i":{"x":0.67,"y":0},"s":[629.5,717.5],"t":33},{"o":{"x":0.32,"y":0},"i":{"x":0.67,"y":0},"s":[577,663],"t":69},{"s":[577,663],"t":129}]},"r":{"a":1,"k":[{"o":{"x":0.32,"y":0},"i":{"x":0.67,"y":0},"s":[0],"t":0},{"o":{"x":0.32,"y":0},"i":{"x":0.67,"y":0},"s":[0],"t":30.06},{"o":{"x":0.32,"y":0},"i":{"x":0.67,"y":0},"s":[0],"t":33},{"o":{"x":0.32,"y":0},"i":{"x":0.67,"y":0},"s":[0],"t":69},{"s":[0],"t":129}]},"sa":{"a":0,"k":0},"o":{"a":1,"k":[{"o":{"x":0.32,"y":0},"i":{"x":0.67,"y":0},"s":[0],"t":0},{"o":{"x":0.32,"y":0},"i":{"x":0.67,"y":0},"s":[0],"t":30.06},{"o":{"x":0.32,"y":0},"i":{"x":0.67,"y":0},"s":[100],"t":33},{"o":{"x":0.32,"y":0},"i":{"x":0.67,"y":0},"s":[100],"t":69},{"s":[100],"t":129}]}},"shapes":[{"ty":"sh","bm":0,"hd":false,"nm":"","d":1,"ks":{"a":1,"k":[{"o":{"x":0.32,"y":0},"i":{"x":0.67,"y":0},"s":[{"c":true,"i":[[0,0],[-64.43,15.76],[53.39,-2.02]],"o":[[19.28,-28.27],[-48.68,30.03],[0,0]],"v":[[0,51],[129,0],[0,51]]}],"t":0},{"o":{"x":0.32,"y":0},"i":{"x":0.67,"y":0},"s":[{"c":true,"i":[[0,0],[-64.43,15.76],[53.39,-2.02]],"o":[[19.28,-28.27],[-48.68,30.03],[0,0]],"v":[[0,51],[129,0],[0,51]]}],"t":30.06},{"o":{"x":0.32,"y":0},"i":{"x":0.67,"y":0},"s":[{"c":true,"i":[[0,0],[-64.43,15.76],[53.39,-2.02]],"o":[[19.28,-28.27],[-48.68,30.03],[0,0]],"v":[[0,51],[129,0],[0,51]]}],"t":33},{"o":{"x":0.32,"y":0},"i":{"x":0.67,"y":0},"s":[{"c":true,"i":[[0,0],[-36.96,9.27],[30.62,-1.19]],"o":[[11.06,-16.63],[-27.92,17.66],[0,0]],"v":[[0,30],[74,0],[0,30]]}],"t":69},{"s":[{"c":true,"i":[[0,0],[-36.96,9.27],[30.62,-1.19]],"o":[[11.06,-16.63],[-27.92,17.66],[0,0]],"v":[[0,30],[74,0],[0,30]]}],"t":129}]}},{"ty":"fl","bm":0,"hd":false,"nm":"","c":{"a":1,"k":[{"o":{"x":0.32,"y":0},"i":{"x":0.67,"y":0},"s":[0.2902,0.6,0.3765],"t":0},{"o":{"x":0.32,"y":0},"i":{"x":0.67,"y":0},"s":[0.2902,0.6,0.3765],"t":30.06},{"o":{"x":0.32,"y":0},"i":{"x":0.67,"y":0},"s":[0.2902,0.6,0.3765],"t":33},{"o":{"x":0.32,"y":0},"i":{"x":0.67,"y":0},"s":[0.2902,0.6,0.3765],"t":69},{"s":[0.2902,0.6,0.3765],"t":129}]},"r":1,"o":{"a":1,"k":[{"o":{"x":0.32,"y":0},"i":{"x":0.67,"y":0},"s":[100],"t":0},{"o":{"x":0.32,"y":0},"i":{"x":0.67,"y":0},"s":[100],"t":30.06},{"o":{"x":0.32,"y":0},"i":{"x":0.67,"y":0},"s":[100],"t":33},{"o":{"x":0.32,"y":0},"i":{"x":0.67,"y":0},"s":[100],"t":69},{"s":[100],"t":129}]}}],"ind":7},{"ty":4,"nm":"Vector 41","sr":1,"st":0,"op":130.06,"ip":0,"hd":false,"ddd":0,"bm":0,"hasMask":false,"ao":0,"ks":{"a":{"a":1,"k":[{"o":{"x":0.32,"y":0},"i":{"x":0.67,"y":0},"s":[60,59],"t":0},{"o":{"x":0.32,"y":0},"i":{"x":0.67,"y":0},"s":[60,59],"t":30.06},{"o":{"x":0.32,"y":0},"i":{"x":0.67,"y":0},"s":[60,59],"t":33},{"o":{"x":0.32,"y":0},"i":{"x":0.67,"y":0},"s":[34,33.5],"t":69},{"s":[34,33.5],"t":129}]},"s":{"a":1,"k":[{"o":{"x":0.32,"y":0},"i":{"x":0.67,"y":0},"s":[100,100],"t":0},{"o":{"x":0.32,"y":0},"i":{"x":0.67,"y":0},"s":[100,100],"t":30.06},{"o":{"x":0.32,"y":0},"i":{"x":0.67,"y":0},"s":[100,100],"t":33},{"o":{"x":0.32,"y":0},"i":{"x":0.67,"y":0},"s":[100,100],"t":69},{"s":[100,100],"t":129}]},"sk":{"a":0,"k":0},"p":{"a":1,"k":[{"o":{"x":0.32,"y":0},"i":{"x":0.67,"y":0},"s":[634,664],"t":0},{"o":{"x":0.32,"y":0},"i":{"x":0.67,"y":0},"s":[634,664],"t":30.06},{"o":{"x":0.32,"y":0},"i":{"x":0.67,"y":0},"s":[634,664],"t":33},{"o":{"x":0.32,"y":0},"i":{"x":0.67,"y":0},"s":[580,632.5],"t":69},{"s":[580,632.5],"t":129}]},"r":{"a":1,"k":[{"o":{"x":0.32,"y":0},"i":{"x":0.67,"y":0},"s":[0],"t":0},{"o":{"x":0.32,"y":0},"i":{"x":0.67,"y":0},"s":[0],"t":30.06},{"o":{"x":0.32,"y":0},"i":{"x":0.67,"y":0},"s":[0],"t":33},{"o":{"x":0.32,"y":0},"i":{"x":0.67,"y":0},"s":[0],"t":69},{"s":[0],"t":129}]},"sa":{"a":0,"k":0},"o":{"a":1,"k":[{"o":{"x":0.32,"y":0},"i":{"x":0.67,"y":0},"s":[0],"t":0},{"o":{"x":0.32,"y":0},"i":{"x":0.67,"y":0},"s":[0],"t":30.06},{"o":{"x":0.32,"y":0},"i":{"x":0.67,"y":0},"s":[100],"t":33},{"o":{"x":0.32,"y":0},"i":{"x":0.67,"y":0},"s":[100],"t":69},{"s":[100],"t":129}]}},"shapes":[{"ty":"sh","bm":0,"hd":false,"nm":"","d":1,"ks":{"a":1,"k":[{"o":{"x":0.32,"y":0},"i":{"x":0.67,"y":0},"s":[{"c":true,"i":[[0,0],[-70.75,52.07],[56.88,-24.79]],"o":[[0.75,-34.5],[-40.56,59.44],[0,0]],"v":[[0,118],[120,0],[0,118]]}],"t":0},{"o":{"x":0.32,"y":0},"i":{"x":0.67,"y":0},"s":[{"c":true,"i":[[0,0],[-70.75,52.07],[56.88,-24.79]],"o":[[0.75,-34.5],[-40.56,59.44],[0,0]],"v":[[0,118],[120,0],[0,118]]}],"t":30.06},{"o":{"x":0.32,"y":0},"i":{"x":0.67,"y":0},"s":[{"c":true,"i":[[0,0],[-70.75,52.07],[56.88,-24.79]],"o":[[0.75,-34.5],[-40.56,59.44],[0,0]],"v":[[0,118],[120,0],[0,118]]}],"t":33},{"o":{"x":0.32,"y":0},"i":{"x":0.67,"y":0},"s":[{"c":true,"i":[[0,0],[-40.09,29.57],[32.23,-14.08]],"o":[[0.43,-19.59],[-22.98,33.75],[0,0]],"v":[[0,67],[68,0],[0,67]]}],"t":69},{"s":[{"c":true,"i":[[0,0],[-40.09,29.57],[32.23,-14.08]],"o":[[0.43,-19.59],[-22.98,33.75],[0,0]],"v":[[0,67],[68,0],[0,67]]}],"t":129}]}},{"ty":"fl","bm":0,"hd":false,"nm":"","c":{"a":1,"k":[{"o":{"x":0.32,"y":0},"i":{"x":0.67,"y":0},"s":[0.2902,0.6,0.3765],"t":0},{"o":{"x":0.32,"y":0},"i":{"x":0.67,"y":0},"s":[0.2902,0.6,0.3765],"t":30.06},{"o":{"x":0.32,"y":0},"i":{"x":0.67,"y":0},"s":[0.2902,0.6,0.3765],"t":33},{"o":{"x":0.32,"y":0},"i":{"x":0.67,"y":0},"s":[0.2902,0.6,0.3765],"t":69},{"s":[0.2902,0.6,0.3765],"t":129}]},"r":1,"o":{"a":1,"k":[{"o":{"x":0.32,"y":0},"i":{"x":0.67,"y":0},"s":[100],"t":0},{"o":{"x":0.32,"y":0},"i":{"x":0.67,"y":0},"s":[100],"t":30.06},{"o":{"x":0.32,"y":0},"i":{"x":0.67,"y":0},"s":[100],"t":33},{"o":{"x":0.32,"y":0},"i":{"x":0.67,"y":0},"s":[100],"t":69},{"s":[100],"t":129}]}}],"ind":8},{"ty":4,"nm":"Vector 40","sr":1,"st":0,"op":130.06,"ip":0,"hd":false,"ddd":0,"bm":0,"hasMask":false,"ao":0,"ks":{"a":{"a":1,"k":[{"o":{"x":0.32,"y":0},"i":{"x":0.67,"y":0},"s":[43.5,63.5],"t":0},{"o":{"x":0.32,"y":0},"i":{"x":0.67,"y":0},"s":[43.5,63.5],"t":30.06},{"o":{"x":0.32,"y":0},"i":{"x":0.67,"y":0},"s":[43.5,63.5],"t":33},{"o":{"x":0.32,"y":0},"i":{"x":0.67,"y":0},"s":[25,36.5],"t":69},{"s":[25,36.5],"t":129}]},"s":{"a":1,"k":[{"o":{"x":0.32,"y":0},"i":{"x":0.67,"y":0},"s":[100,100],"t":0},{"o":{"x":0.32,"y":0},"i":{"x":0.67,"y":0},"s":[100,100],"t":30.06},{"o":{"x":0.32,"y":0},"i":{"x":0.67,"y":0},"s":[100,100],"t":33},{"o":{"x":0.32,"y":0},"i":{"x":0.67,"y":0},"s":[100,100],"t":69},{"s":[100,100],"t":129}]},"sk":{"a":0,"k":0},"p":{"a":1,"k":[{"o":{"x":0.32,"y":0},"i":{"x":0.67,"y":0},"s":[590.5,659.5],"t":0},{"o":{"x":0.32,"y":0},"i":{"x":0.67,"y":0},"s":[590.5,659.5],"t":30.06},{"o":{"x":0.32,"y":0},"i":{"x":0.67,"y":0},"s":[590.5,659.5],"t":33},{"o":{"x":0.32,"y":0},"i":{"x":0.67,"y":0},"s":[555,629.5],"t":69},{"s":[555,629.5],"t":129}]},"r":{"a":1,"k":[{"o":{"x":0.32,"y":0},"i":{"x":0.67,"y":0},"s":[0],"t":0},{"o":{"x":0.32,"y":0},"i":{"x":0.67,"y":0},"s":[0],"t":30.06},{"o":{"x":0.32,"y":0},"i":{"x":0.67,"y":0},"s":[0],"t":33},{"o":{"x":0.32,"y":0},"i":{"x":0.67,"y":0},"s":[0],"t":69},{"s":[0],"t":129}]},"sa":{"a":0,"k":0},"o":{"a":1,"k":[{"o":{"x":0.32,"y":0},"i":{"x":0.67,"y":0},"s":[0],"t":0},{"o":{"x":0.32,"y":0},"i":{"x":0.67,"y":0},"s":[0],"t":30.06},{"o":{"x":0.32,"y":0},"i":{"x":0.67,"y":0},"s":[100],"t":33},{"o":{"x":0.32,"y":0},"i":{"x":0.67,"y":0},"s":[100],"t":69},{"s":[100],"t":129}]}},"shapes":[{"ty":"sh","bm":0,"hd":false,"nm":"","d":1,"ks":{"a":1,"k":[{"o":{"x":0.32,"y":0},"i":{"x":0.67,"y":0},"s":[{"c":true,"i":[[0,0],[-51.56,52.05],[30.43,-13.5]],"o":[[11.78,-46.55],[-37.13,79.6],[0,0]],"v":[[0,127],[87,0],[0,127]]}],"t":0},{"o":{"x":0.32,"y":0},"i":{"x":0.67,"y":0},"s":[{"c":true,"i":[[0,0],[-51.56,52.05],[30.43,-13.5]],"o":[[11.78,-46.55],[-37.13,79.6],[0,0]],"v":[[0,127],[87,0],[0,127]]}],"t":30.06},{"o":{"x":0.32,"y":0},"i":{"x":0.67,"y":0},"s":[{"c":true,"i":[[0,0],[-51.56,52.05],[30.43,-13.5]],"o":[[11.78,-46.55],[-37.13,79.6],[0,0]],"v":[[0,127],[87,0],[0,127]]}],"t":33},{"o":{"x":0.32,"y":0},"i":{"x":0.67,"y":0},"s":[{"c":true,"i":[[0,0],[-29.63,29.92],[17.49,-7.76]],"o":[[6.77,-26.76],[-21.34,45.76],[0,0]],"v":[[0,73],[50,0],[0,73]]}],"t":69},{"s":[{"c":true,"i":[[0,0],[-29.63,29.92],[17.49,-7.76]],"o":[[6.77,-26.76],[-21.34,45.76],[0,0]],"v":[[0,73],[50,0],[0,73]]}],"t":129}]}},{"ty":"fl","bm":0,"hd":false,"nm":"","c":{"a":1,"k":[{"o":{"x":0.32,"y":0},"i":{"x":0.67,"y":0},"s":[0.2902,0.6,0.3765],"t":0},{"o":{"x":0.32,"y":0},"i":{"x":0.67,"y":0},"s":[0.2902,0.6,0.3765],"t":30.06},{"o":{"x":0.32,"y":0},"i":{"x":0.67,"y":0},"s":[0.2902,0.6,0.3765],"t":33},{"o":{"x":0.32,"y":0},"i":{"x":0.67,"y":0},"s":[0.2902,0.6,0.3765],"t":69},{"s":[0.2902,0.6,0.3765],"t":129}]},"r":1,"o":{"a":1,"k":[{"o":{"x":0.32,"y":0},"i":{"x":0.67,"y":0},"s":[100],"t":0},{"o":{"x":0.32,"y":0},"i":{"x":0.67,"y":0},"s":[100],"t":30.06},{"o":{"x":0.32,"y":0},"i":{"x":0.67,"y":0},"s":[100],"t":33},{"o":{"x":0.32,"y":0},"i":{"x":0.67,"y":0},"s":[100],"t":69},{"s":[100],"t":129}]}}],"ind":9},{"ty":4,"nm":"Vector 36","sr":1,"st":0,"op":130.06,"ip":0,"hd":false,"ddd":0,"bm":0,"hasMask":false,"ao":0,"ks":{"a":{"a":1,"k":[{"o":{"x":0.32,"y":0},"i":{"x":0.67,"y":0},"s":[74,30],"t":0},{"o":{"x":0.32,"y":0},"i":{"x":0.67,"y":0},"s":[74,30],"t":18.06},{"o":{"x":0.32,"y":0},"i":{"x":0.67,"y":0},"s":[74,30],"t":21},{"o":{"x":0.32,"y":0},"i":{"x":0.67,"y":0},"s":[74,30],"t":24},{"o":{"x":0.32,"y":0},"i":{"x":0.67,"y":0},"s":[74,30],"t":27},{"o":{"x":0.32,"y":0},"i":{"x":0.67,"y":0},"s":[74,30],"t":30},{"o":{"x":0.32,"y":0},"i":{"x":0.67,"y":0},"s":[74,30],"t":33},{"o":{"x":0.32,"y":0},"i":{"x":0.67,"y":0},"s":[42.5,17],"t":69},{"s":[42.5,17],"t":129}]},"s":{"a":1,"k":[{"o":{"x":0.32,"y":0},"i":{"x":0.67,"y":0},"s":[100,100],"t":0},{"o":{"x":0.32,"y":0},"i":{"x":0.67,"y":0},"s":[100,100],"t":18.06},{"o":{"x":0.32,"y":0},"i":{"x":0.67,"y":0},"s":[100,100],"t":21},{"o":{"x":0.32,"y":0},"i":{"x":0.67,"y":0},"s":[100,100],"t":24},{"o":{"x":0.32,"y":0},"i":{"x":0.67,"y":0},"s":[100,100],"t":27},{"o":{"x":0.32,"y":0},"i":{"x":0.67,"y":0},"s":[100,100],"t":30},{"o":{"x":0.32,"y":0},"i":{"x":0.67,"y":0},"s":[100,100],"t":33},{"o":{"x":0.32,"y":0},"i":{"x":0.67,"y":0},"s":[100,100],"t":69},{"s":[100,100],"t":129}]},"sk":{"a":0,"k":0},"p":{"a":1,"k":[{"o":{"x":0.32,"y":0},"i":{"x":0.67,"y":0},"s":[597,436],"t":0},{"o":{"x":0.32,"y":0},"i":{"x":0.67,"y":0},"s":[597,436],"t":18.06},{"o":{"x":0.32,"y":0},"i":{"x":0.67,"y":0},"s":[597,436],"t":21},{"o":{"x":0.32,"y":0},"i":{"x":0.67,"y":0},"s":[597,436],"t":24},{"o":{"x":0.32,"y":0},"i":{"x":0.67,"y":0},"s":[597,436],"t":27},{"o":{"x":0.32,"y":0},"i":{"x":0.67,"y":0},"s":[597,436],"t":30},{"o":{"x":0.32,"y":0},"i":{"x":0.67,"y":0},"s":[597,436],"t":33},{"o":{"x":0.32,"y":0},"i":{"x":0.67,"y":0},"s":[558.5,502],"t":69},{"s":[558.5,502],"t":129}]},"r":{"a":1,"k":[{"o":{"x":0.32,"y":0},"i":{"x":0.67,"y":0},"s":[0],"t":0},{"o":{"x":0.32,"y":0},"i":{"x":0.67,"y":0},"s":[0],"t":18.06},{"o":{"x":0.32,"y":0},"i":{"x":0.67,"y":0},"s":[0],"t":21},{"o":{"x":0.32,"y":0},"i":{"x":0.67,"y":0},"s":[0],"t":24},{"o":{"x":0.32,"y":0},"i":{"x":0.67,"y":0},"s":[0],"t":27},{"o":{"x":0.32,"y":0},"i":{"x":0.67,"y":0},"s":[0],"t":30},{"o":{"x":0.32,"y":0},"i":{"x":0.67,"y":0},"s":[0],"t":33},{"o":{"x":0.32,"y":0},"i":{"x":0.67,"y":0},"s":[0],"t":69},{"s":[0],"t":129}]},"sa":{"a":0,"k":0},"o":{"a":1,"k":[{"o":{"x":0.32,"y":0},"i":{"x":0.67,"y":0},"s":[0],"t":0},{"o":{"x":0.32,"y":0},"i":{"x":0.67,"y":0},"s":[0],"t":18.06},{"o":{"x":0.32,"y":0},"i":{"x":0.67,"y":0},"s":[100],"t":21},{"o":{"x":0.32,"y":0},"i":{"x":0.67,"y":0},"s":[100],"t":24},{"o":{"x":0.32,"y":0},"i":{"x":0.67,"y":0},"s":[100],"t":27},{"o":{"x":0.32,"y":0},"i":{"x":0.67,"y":0},"s":[100],"t":30},{"o":{"x":0.32,"y":0},"i":{"x":0.67,"y":0},"s":[100],"t":33},{"o":{"x":0.32,"y":0},"i":{"x":0.67,"y":0},"s":[100],"t":69},{"s":[100],"t":129}]}},"shapes":[{"ty":"sh","bm":0,"hd":false,"nm":"","d":1,"ks":{"a":1,"k":[{"o":{"x":0.32,"y":0},"i":{"x":0.67,"y":0},"s":[{"c":true,"i":[[0,0],[-73.92,18.54],[61.25,-2.37]],"o":[[22.12,-33.26],[-55.85,35.33],[0,0]],"v":[[0,60],[148,0],[0,60]]}],"t":0},{"o":{"x":0.32,"y":0},"i":{"x":0.67,"y":0},"s":[{"c":true,"i":[[0,0],[-73.92,18.54],[61.25,-2.37]],"o":[[22.12,-33.26],[-55.85,35.33],[0,0]],"v":[[0,60],[148,0],[0,60]]}],"t":18.06},{"o":{"x":0.32,"y":0},"i":{"x":0.67,"y":0},"s":[{"c":true,"i":[[0,0],[-73.92,18.54],[61.25,-2.37]],"o":[[22.12,-33.26],[-55.85,35.33],[0,0]],"v":[[0,60],[148,0],[0,60]]}],"t":21},{"o":{"x":0.32,"y":0},"i":{"x":0.67,"y":0},"s":[{"c":true,"i":[[0,0],[-73.92,18.54],[61.25,-2.37]],"o":[[22.12,-33.26],[-55.85,35.33],[0,0]],"v":[[0,60],[148,0],[0,60]]}],"t":24},{"o":{"x":0.32,"y":0},"i":{"x":0.67,"y":0},"s":[{"c":true,"i":[[0,0],[-73.92,18.54],[61.25,-2.37]],"o":[[22.12,-33.26],[-55.85,35.33],[0,0]],"v":[[0,60],[148,0],[0,60]]}],"t":27},{"o":{"x":0.32,"y":0},"i":{"x":0.67,"y":0},"s":[{"c":true,"i":[[0,0],[-73.92,18.54],[61.25,-2.37]],"o":[[22.12,-33.26],[-55.85,35.33],[0,0]],"v":[[0,60],[148,0],[0,60]]}],"t":30},{"o":{"x":0.32,"y":0},"i":{"x":0.67,"y":0},"s":[{"c":true,"i":[[0,0],[-73.92,18.54],[61.25,-2.37]],"o":[[22.12,-33.26],[-55.85,35.33],[0,0]],"v":[[0,60],[148,0],[0,60]]}],"t":33},{"o":{"x":0.32,"y":0},"i":{"x":0.67,"y":0},"s":[{"c":true,"i":[[0,0],[-42.45,10.51],[35.18,-1.34]],"o":[[12.71,-18.84],[-32.08,20.02],[0,0]],"v":[[0,34],[85,0],[0,34]]}],"t":69},{"s":[{"c":true,"i":[[0,0],[-42.45,10.51],[35.18,-1.34]],"o":[[12.71,-18.84],[-32.08,20.02],[0,0]],"v":[[0,34],[85,0],[0,34]]}],"t":129}]}},{"ty":"fl","bm":0,"hd":false,"nm":"","c":{"a":1,"k":[{"o":{"x":0.32,"y":0},"i":{"x":0.67,"y":0},"s":[0.2902,0.6,0.3765],"t":0},{"o":{"x":0.32,"y":0},"i":{"x":0.67,"y":0},"s":[0.2902,0.6,0.3765],"t":18.06},{"o":{"x":0.32,"y":0},"i":{"x":0.67,"y":0},"s":[0.2902,0.6,0.3765],"t":21},{"o":{"x":0.32,"y":0},"i":{"x":0.67,"y":0},"s":[0.2902,0.6,0.3765],"t":24},{"o":{"x":0.32,"y":0},"i":{"x":0.67,"y":0},"s":[0.2902,0.6,0.3765],"t":27},{"o":{"x":0.32,"y":0},"i":{"x":0.67,"y":0},"s":[0.2902,0.6,0.3765],"t":30},{"o":{"x":0.32,"y":0},"i":{"x":0.67,"y":0},"s":[0.2902,0.6,0.3765],"t":33},{"o":{"x":0.32,"y":0},"i":{"x":0.67,"y":0},"s":[0.2902,0.6,0.3765],"t":69},{"s":[0.2902,0.6,0.3765],"t":129}]},"r":1,"o":{"a":1,"k":[{"o":{"x":0.32,"y":0},"i":{"x":0.67,"y":0},"s":[100],"t":0},{"o":{"x":0.32,"y":0},"i":{"x":0.67,"y":0},"s":[100],"t":18.06},{"o":{"x":0.32,"y":0},"i":{"x":0.67,"y":0},"s":[100],"t":21},{"o":{"x":0.32,"y":0},"i":{"x":0.67,"y":0},"s":[100],"t":24},{"o":{"x":0.32,"y":0},"i":{"x":0.67,"y":0},"s":[100],"t":27},{"o":{"x":0.32,"y":0},"i":{"x":0.67,"y":0},"s":[100],"t":30},{"o":{"x":0.32,"y":0},"i":{"x":0.67,"y":0},"s":[100],"t":33},{"o":{"x":0.32,"y":0},"i":{"x":0.67,"y":0},"s":[100],"t":69},{"s":[100],"t":129}]}}],"ind":10},{"ty":4,"nm":"Vector 35","sr":1,"st":0,"op":130.06,"ip":0,"hd":false,"ddd":0,"bm":0,"hasMask":false,"ao":0,"ks":{"a":{"a":1,"k":[{"o":{"x":0.32,"y":0},"i":{"x":0.67,"y":0},"s":[69.5,69.5],"t":0},{"o":{"x":0.32,"y":0},"i":{"x":0.67,"y":0},"s":[69.5,69.5],"t":18.06},{"o":{"x":0.32,"y":0},"i":{"x":0.67,"y":0},"s":[69.5,69.5],"t":21},{"o":{"x":0.32,"y":0},"i":{"x":0.67,"y":0},"s":[69.5,69.5],"t":24},{"o":{"x":0.32,"y":0},"i":{"x":0.67,"y":0},"s":[69.5,69.5],"t":27},{"o":{"x":0.32,"y":0},"i":{"x":0.67,"y":0},"s":[69.5,69.5],"t":30},{"o":{"x":0.32,"y":0},"i":{"x":0.67,"y":0},"s":[69.5,69.5],"t":33},{"o":{"x":0.32,"y":0},"i":{"x":0.67,"y":0},"s":[40,40],"t":69},{"s":[40,40],"t":129}]},"s":{"a":1,"k":[{"o":{"x":0.32,"y":0},"i":{"x":0.67,"y":0},"s":[100,100],"t":0},{"o":{"x":0.32,"y":0},"i":{"x":0.67,"y":0},"s":[100,100],"t":18.06},{"o":{"x":0.32,"y":0},"i":{"x":0.67,"y":0},"s":[100,100],"t":21},{"o":{"x":0.32,"y":0},"i":{"x":0.67,"y":0},"s":[100,100],"t":24},{"o":{"x":0.32,"y":0},"i":{"x":0.67,"y":0},"s":[100,100],"t":27},{"o":{"x":0.32,"y":0},"i":{"x":0.67,"y":0},"s":[100,100],"t":30},{"o":{"x":0.32,"y":0},"i":{"x":0.67,"y":0},"s":[100,100],"t":33},{"o":{"x":0.32,"y":0},"i":{"x":0.67,"y":0},"s":[100,100],"t":69},{"s":[100,100],"t":129}]},"sk":{"a":0,"k":0},"p":{"a":1,"k":[{"o":{"x":0.32,"y":0},"i":{"x":0.67,"y":0},"s":[606.5,370.5],"t":0},{"o":{"x":0.32,"y":0},"i":{"x":0.67,"y":0},"s":[606.5,370.5],"t":18.06},{"o":{"x":0.32,"y":0},"i":{"x":0.67,"y":0},"s":[606.5,370.5],"t":21},{"o":{"x":0.32,"y":0},"i":{"x":0.67,"y":0},"s":[606.5,370.5],"t":24},{"o":{"x":0.32,"y":0},"i":{"x":0.67,"y":0},"s":[606.5,370.5],"t":27},{"o":{"x":0.32,"y":0},"i":{"x":0.67,"y":0},"s":[606.5,370.5],"t":30},{"o":{"x":0.32,"y":0},"i":{"x":0.67,"y":0},"s":[606.5,370.5],"t":33},{"o":{"x":0.32,"y":0},"i":{"x":0.67,"y":0},"s":[564,464],"t":69},{"s":[564,464],"t":129}]},"r":{"a":1,"k":[{"o":{"x":0.32,"y":0},"i":{"x":0.67,"y":0},"s":[0],"t":0},{"o":{"x":0.32,"y":0},"i":{"x":0.67,"y":0},"s":[0],"t":18.06},{"o":{"x":0.32,"y":0},"i":{"x":0.67,"y":0},"s":[0],"t":21},{"o":{"x":0.32,"y":0},"i":{"x":0.67,"y":0},"s":[0],"t":24},{"o":{"x":0.32,"y":0},"i":{"x":0.67,"y":0},"s":[0],"t":27},{"o":{"x":0.32,"y":0},"i":{"x":0.67,"y":0},"s":[0],"t":30},{"o":{"x":0.32,"y":0},"i":{"x":0.67,"y":0},"s":[0],"t":33},{"o":{"x":0.32,"y":0},"i":{"x":0.67,"y":0},"s":[0],"t":69},{"s":[0],"t":129}]},"sa":{"a":0,"k":0},"o":{"a":1,"k":[{"o":{"x":0.32,"y":0},"i":{"x":0.67,"y":0},"s":[0],"t":0},{"o":{"x":0.32,"y":0},"i":{"x":0.67,"y":0},"s":[0],"t":18.06},{"o":{"x":0.32,"y":0},"i":{"x":0.67,"y":0},"s":[100],"t":21},{"o":{"x":0.32,"y":0},"i":{"x":0.67,"y":0},"s":[100],"t":24},{"o":{"x":0.32,"y":0},"i":{"x":0.67,"y":0},"s":[100],"t":27},{"o":{"x":0.32,"y":0},"i":{"x":0.67,"y":0},"s":[100],"t":30},{"o":{"x":0.32,"y":0},"i":{"x":0.67,"y":0},"s":[100],"t":33},{"o":{"x":0.32,"y":0},"i":{"x":0.67,"y":0},"s":[100],"t":69},{"s":[100],"t":129}]}},"shapes":[{"ty":"sh","bm":0,"hd":false,"nm":"","d":1,"ks":{"a":1,"k":[{"o":{"x":0.32,"y":0},"i":{"x":0.67,"y":0},"s":[{"c":true,"i":[[0,0],[-81.95,61.34],[65.89,-29.2]],"o":[[0.87,-40.64],[-46.98,70.01],[0,0]],"v":[[0,139],[139,0],[0,139]]}],"t":0},{"o":{"x":0.32,"y":0},"i":{"x":0.67,"y":0},"s":[{"c":true,"i":[[0,0],[-81.95,61.34],[65.89,-29.2]],"o":[[0.87,-40.64],[-46.98,70.01],[0,0]],"v":[[0,139],[139,0],[0,139]]}],"t":18.06},{"o":{"x":0.32,"y":0},"i":{"x":0.67,"y":0},"s":[{"c":true,"i":[[0,0],[-81.95,61.34],[65.89,-29.2]],"o":[[0.87,-40.64],[-46.98,70.01],[0,0]],"v":[[0,139],[139,0],[0,139]]}],"t":21},{"o":{"x":0.32,"y":0},"i":{"x":0.67,"y":0},"s":[{"c":true,"i":[[0,0],[-81.95,61.34],[65.89,-29.2]],"o":[[0.87,-40.64],[-46.98,70.01],[0,0]],"v":[[0,139],[139,0],[0,139]]}],"t":24},{"o":{"x":0.32,"y":0},"i":{"x":0.67,"y":0},"s":[{"c":true,"i":[[0,0],[-81.95,61.34],[65.89,-29.2]],"o":[[0.87,-40.64],[-46.98,70.01],[0,0]],"v":[[0,139],[139,0],[0,139]]}],"t":27},{"o":{"x":0.32,"y":0},"i":{"x":0.67,"y":0},"s":[{"c":true,"i":[[0,0],[-81.95,61.34],[65.89,-29.2]],"o":[[0.87,-40.64],[-46.98,70.01],[0,0]],"v":[[0,139],[139,0],[0,139]]}],"t":30},{"o":{"x":0.32,"y":0},"i":{"x":0.67,"y":0},"s":[{"c":true,"i":[[0,0],[-81.95,61.34],[65.89,-29.2]],"o":[[0.87,-40.64],[-46.98,70.01],[0,0]],"v":[[0,139],[139,0],[0,139]]}],"t":33},{"o":{"x":0.32,"y":0},"i":{"x":0.67,"y":0},"s":[{"c":true,"i":[[0,0],[-47.17,35.3],[37.92,-16.81]],"o":[[0.5,-23.39],[-27.04,40.3],[0,0]],"v":[[0,80],[80,0],[0,80]]}],"t":69},{"s":[{"c":true,"i":[[0,0],[-47.17,35.3],[37.92,-16.81]],"o":[[0.5,-23.39],[-27.04,40.3],[0,0]],"v":[[0,80],[80,0],[0,80]]}],"t":129}]}},{"ty":"fl","bm":0,"hd":false,"nm":"","c":{"a":1,"k":[{"o":{"x":0.32,"y":0},"i":{"x":0.67,"y":0},"s":[0.2902,0.6,0.3765],"t":0},{"o":{"x":0.32,"y":0},"i":{"x":0.67,"y":0},"s":[0.2902,0.6,0.3765],"t":18.06},{"o":{"x":0.32,"y":0},"i":{"x":0.67,"y":0},"s":[0.2902,0.6,0.3765],"t":21},{"o":{"x":0.32,"y":0},"i":{"x":0.67,"y":0},"s":[0.2902,0.6,0.3765],"t":24},{"o":{"x":0.32,"y":0},"i":{"x":0.67,"y":0},"s":[0.2902,0.6,0.3765],"t":27},{"o":{"x":0.32,"y":0},"i":{"x":0.67,"y":0},"s":[0.2902,0.6,0.3765],"t":30},{"o":{"x":0.32,"y":0},"i":{"x":0.67,"y":0},"s":[0.2902,0.6,0.3765],"t":33},{"o":{"x":0.32,"y":0},"i":{"x":0.67,"y":0},"s":[0.2902,0.6,0.3765],"t":69},{"s":[0.2902,0.6,0.3765],"t":129}]},"r":1,"o":{"a":1,"k":[{"o":{"x":0.32,"y":0},"i":{"x":0.67,"y":0},"s":[100],"t":0},{"o":{"x":0.32,"y":0},"i":{"x":0.67,"y":0},"s":[100],"t":18.06},{"o":{"x":0.32,"y":0},"i":{"x":0.67,"y":0},"s":[100],"t":21},{"o":{"x":0.32,"y":0},"i":{"x":0.67,"y":0},"s":[100],"t":24},{"o":{"x":0.32,"y":0},"i":{"x":0.67,"y":0},"s":[100],"t":27},{"o":{"x":0.32,"y":0},"i":{"x":0.67,"y":0},"s":[100],"t":30},{"o":{"x":0.32,"y":0},"i":{"x":0.67,"y":0},"s":[100],"t":33},{"o":{"x":0.32,"y":0},"i":{"x":0.67,"y":0},"s":[100],"t":69},{"s":[100],"t":129}]}}],"ind":11},{"ty":4,"nm":"Vector 34","sr":1,"st":0,"op":130.06,"ip":0,"hd":false,"ddd":0,"bm":0,"hasMask":false,"ao":0,"ks":{"a":{"a":1,"k":[{"o":{"x":0.32,"y":0},"i":{"x":0.67,"y":0},"s":[51.5,73],"t":0},{"o":{"x":0.32,"y":0},"i":{"x":0.67,"y":0},"s":[51.5,73],"t":18.06},{"o":{"x":0.32,"y":0},"i":{"x":0.67,"y":0},"s":[51.5,73],"t":21},{"o":{"x":0.32,"y":0},"i":{"x":0.67,"y":0},"s":[51.5,73],"t":24},{"o":{"x":0.32,"y":0},"i":{"x":0.67,"y":0},"s":[51.5,73],"t":27},{"o":{"x":0.32,"y":0},"i":{"x":0.67,"y":0},"s":[51.5,73],"t":30},{"o":{"x":0.32,"y":0},"i":{"x":0.67,"y":0},"s":[51.5,73],"t":33},{"o":{"x":0.32,"y":0},"i":{"x":0.67,"y":0},"s":[29.5,42],"t":69},{"s":[29.5,42],"t":129}]},"s":{"a":1,"k":[{"o":{"x":0.32,"y":0},"i":{"x":0.67,"y":0},"s":[100,100],"t":0},{"o":{"x":0.32,"y":0},"i":{"x":0.67,"y":0},"s":[100,100],"t":18.06},{"o":{"x":0.32,"y":0},"i":{"x":0.67,"y":0},"s":[100,100],"t":21},{"o":{"x":0.32,"y":0},"i":{"x":0.67,"y":0},"s":[100,100],"t":24},{"o":{"x":0.32,"y":0},"i":{"x":0.67,"y":0},"s":[100,100],"t":27},{"o":{"x":0.32,"y":0},"i":{"x":0.67,"y":0},"s":[100,100],"t":30},{"o":{"x":0.32,"y":0},"i":{"x":0.67,"y":0},"s":[100,100],"t":33},{"o":{"x":0.32,"y":0},"i":{"x":0.67,"y":0},"s":[100,100],"t":69},{"s":[100,100],"t":129}]},"sk":{"a":0,"k":0},"p":{"a":1,"k":[{"o":{"x":0.32,"y":0},"i":{"x":0.67,"y":0},"s":[552.5,367],"t":0},{"o":{"x":0.32,"y":0},"i":{"x":0.67,"y":0},"s":[552.5,367],"t":18.06},{"o":{"x":0.32,"y":0},"i":{"x":0.67,"y":0},"s":[552.5,367],"t":21},{"o":{"x":0.32,"y":0},"i":{"x":0.67,"y":0},"s":[552.5,367],"t":24},{"o":{"x":0.32,"y":0},"i":{"x":0.67,"y":0},"s":[552.5,367],"t":27},{"o":{"x":0.32,"y":0},"i":{"x":0.67,"y":0},"s":[552.5,367],"t":30},{"o":{"x":0.32,"y":0},"i":{"x":0.67,"y":0},"s":[552.5,367],"t":33},{"o":{"x":0.32,"y":0},"i":{"x":0.67,"y":0},"s":[533.5,462],"t":69},{"s":[533.5,462],"t":129}]},"r":{"a":1,"k":[{"o":{"x":0.32,"y":0},"i":{"x":0.67,"y":0},"s":[0],"t":0},{"o":{"x":0.32,"y":0},"i":{"x":0.67,"y":0},"s":[0],"t":18.06},{"o":{"x":0.32,"y":0},"i":{"x":0.67,"y":0},"s":[0],"t":21},{"o":{"x":0.32,"y":0},"i":{"x":0.67,"y":0},"s":[0],"t":24},{"o":{"x":0.32,"y":0},"i":{"x":0.67,"y":0},"s":[0],"t":27},{"o":{"x":0.32,"y":0},"i":{"x":0.67,"y":0},"s":[0],"t":30},{"o":{"x":0.32,"y":0},"i":{"x":0.67,"y":0},"s":[0],"t":33},{"o":{"x":0.32,"y":0},"i":{"x":0.67,"y":0},"s":[0],"t":69},{"s":[0],"t":129}]},"sa":{"a":0,"k":0},"o":{"a":1,"k":[{"o":{"x":0.32,"y":0},"i":{"x":0.67,"y":0},"s":[0],"t":0},{"o":{"x":0.32,"y":0},"i":{"x":0.67,"y":0},"s":[0],"t":18.06},{"o":{"x":0.32,"y":0},"i":{"x":0.67,"y":0},"s":[100],"t":21},{"o":{"x":0.32,"y":0},"i":{"x":0.67,"y":0},"s":[100],"t":24},{"o":{"x":0.32,"y":0},"i":{"x":0.67,"y":0},"s":[100],"t":27},{"o":{"x":0.32,"y":0},"i":{"x":0.67,"y":0},"s":[100],"t":30},{"o":{"x":0.32,"y":0},"i":{"x":0.67,"y":0},"s":[100],"t":33},{"o":{"x":0.32,"y":0},"i":{"x":0.67,"y":0},"s":[100],"t":69},{"s":[100],"t":129}]}},"shapes":[{"ty":"sh","bm":0,"hd":false,"nm":"","d":1,"ks":{"a":1,"k":[{"o":{"x":0.32,"y":0},"i":{"x":0.67,"y":0},"s":[{"c":true,"i":[[0,0],[-61.04,59.84],[36.02,-15.52]],"o":[[13.94,-53.51],[-43.96,91.51],[0,0]],"v":[[0,146],[103,0],[0,146]]}],"t":0},{"o":{"x":0.32,"y":0},"i":{"x":0.67,"y":0},"s":[{"c":true,"i":[[0,0],[-61.04,59.84],[36.02,-15.52]],"o":[[13.94,-53.51],[-43.96,91.51],[0,0]],"v":[[0,146],[103,0],[0,146]]}],"t":18.06},{"o":{"x":0.32,"y":0},"i":{"x":0.67,"y":0},"s":[{"c":true,"i":[[0,0],[-61.04,59.84],[36.02,-15.52]],"o":[[13.94,-53.51],[-43.96,91.51],[0,0]],"v":[[0,146],[103,0],[0,146]]}],"t":21},{"o":{"x":0.32,"y":0},"i":{"x":0.67,"y":0},"s":[{"c":true,"i":[[0,0],[-61.04,59.84],[36.02,-15.52]],"o":[[13.94,-53.51],[-43.96,91.51],[0,0]],"v":[[0,146],[103,0],[0,146]]}],"t":24},{"o":{"x":0.32,"y":0},"i":{"x":0.67,"y":0},"s":[{"c":true,"i":[[0,0],[-61.04,59.84],[36.02,-15.52]],"o":[[13.94,-53.51],[-43.96,91.51],[0,0]],"v":[[0,146],[103,0],[0,146]]}],"t":27},{"o":{"x":0.32,"y":0},"i":{"x":0.67,"y":0},"s":[{"c":true,"i":[[0,0],[-61.04,59.84],[36.02,-15.52]],"o":[[13.94,-53.51],[-43.96,91.51],[0,0]],"v":[[0,146],[103,0],[0,146]]}],"t":30},{"o":{"x":0.32,"y":0},"i":{"x":0.67,"y":0},"s":[{"c":true,"i":[[0,0],[-61.04,59.84],[36.02,-15.52]],"o":[[13.94,-53.51],[-43.96,91.51],[0,0]],"v":[[0,146],[103,0],[0,146]]}],"t":33},{"o":{"x":0.32,"y":0},"i":{"x":0.67,"y":0},"s":[{"c":true,"i":[[0,0],[-34.96,34.43],[20.64,-8.93]],"o":[[7.99,-30.79],[-25.18,52.65],[0,0]],"v":[[0,84],[59,0],[0,84]]}],"t":69},{"s":[{"c":true,"i":[[0,0],[-34.96,34.43],[20.64,-8.93]],"o":[[7.99,-30.79],[-25.18,52.65],[0,0]],"v":[[0,84],[59,0],[0,84]]}],"t":129}]}},{"ty":"fl","bm":0,"hd":false,"nm":"","c":{"a":1,"k":[{"o":{"x":0.32,"y":0},"i":{"x":0.67,"y":0},"s":[0.2902,0.6,0.3765],"t":0},{"o":{"x":0.32,"y":0},"i":{"x":0.67,"y":0},"s":[0.2902,0.6,0.3765],"t":18.06},{"o":{"x":0.32,"y":0},"i":{"x":0.67,"y":0},"s":[0.2902,0.6,0.3765],"t":21},{"o":{"x":0.32,"y":0},"i":{"x":0.67,"y":0},"s":[0.2902,0.6,0.3765],"t":24},{"o":{"x":0.32,"y":0},"i":{"x":0.67,"y":0},"s":[0.2902,0.6,0.3765],"t":27},{"o":{"x":0.32,"y":0},"i":{"x":0.67,"y":0},"s":[0.2902,0.6,0.3765],"t":30},{"o":{"x":0.32,"y":0},"i":{"x":0.67,"y":0},"s":[0.2902,0.6,0.3765],"t":33},{"o":{"x":0.32,"y":0},"i":{"x":0.67,"y":0},"s":[0.2902,0.6,0.3765],"t":69},{"s":[0.2902,0.6,0.3765],"t":129}]},"r":1,"o":{"a":1,"k":[{"o":{"x":0.32,"y":0},"i":{"x":0.67,"y":0},"s":[100],"t":0},{"o":{"x":0.32,"y":0},"i":{"x":0.67,"y":0},"s":[100],"t":18.06},{"o":{"x":0.32,"y":0},"i":{"x":0.67,"y":0},"s":[100],"t":21},{"o":{"x":0.32,"y":0},"i":{"x":0.67,"y":0},"s":[100],"t":24},{"o":{"x":0.32,"y":0},"i":{"x":0.67,"y":0},"s":[100],"t":27},{"o":{"x":0.32,"y":0},"i":{"x":0.67,"y":0},"s":[100],"t":30},{"o":{"x":0.32,"y":0},"i":{"x":0.67,"y":0},"s":[100],"t":33},{"o":{"x":0.32,"y":0},"i":{"x":0.67,"y":0},"s":[100],"t":69},{"s":[100],"t":129}]}}],"ind":12},{"ty":4,"nm":"Vector 43","sr":1,"st":0,"op":130.06,"ip":0,"hd":false,"ddd":0,"bm":0,"hasMask":false,"ao":0,"ks":{"a":{"a":1,"k":[{"o":{"x":0.32,"y":0},"i":{"x":0.67,"y":0},"s":[139,205.5],"t":0},{"o":{"x":0.32,"y":0},"i":{"x":0.67,"y":0},"s":[139,205.5],"t":33.06},{"o":{"x":0.32,"y":0},"i":{"x":0.67,"y":0},"s":[139,205.5],"t":69},{"s":[139,205.5],"t":129}]},"s":{"a":1,"k":[{"o":{"x":0.32,"y":0},"i":{"x":0.67,"y":0},"s":[100,100],"t":0},{"o":{"x":0.32,"y":0},"i":{"x":0.67,"y":0},"s":[100,100],"t":33.06},{"o":{"x":0.32,"y":0},"i":{"x":0.67,"y":0},"s":[100,100],"t":69},{"s":[100,100],"t":129}]},"sk":{"a":0,"k":0},"p":{"a":1,"k":[{"o":{"x":0.32,"y":0},"i":{"x":0.67,"y":0},"s":[554,554.5],"t":0},{"o":{"x":0.32,"y":0},"i":{"x":0.67,"y":0},"s":[554,554.5],"t":33.06},{"o":{"x":0.32,"y":0},"i":{"x":0.67,"y":0},"s":[554,554.5],"t":69},{"s":[554,554.5],"t":129}]},"r":{"a":1,"k":[{"o":{"x":0.32,"y":0},"i":{"x":0.67,"y":0},"s":[0],"t":0},{"o":{"x":0.32,"y":0},"i":{"x":0.67,"y":0},"s":[0],"t":33.06},{"o":{"x":0.32,"y":0},"i":{"x":0.67,"y":0},"s":[0],"t":69},{"s":[0],"t":129}]},"sa":{"a":0,"k":0},"o":{"a":1,"k":[{"o":{"x":0.32,"y":0},"i":{"x":0.67,"y":0},"s":[0],"t":0},{"o":{"x":0.32,"y":0},"i":{"x":0.67,"y":0},"s":[0],"t":33.06},{"o":{"x":0.32,"y":0},"i":{"x":0.67,"y":0},"s":[100],"t":69},{"s":[100],"t":129}]}},"shapes":[{"ty":"sh","bm":0,"hd":false,"nm":"","d":1,"ks":{"a":1,"k":[{"o":{"x":0.32,"y":0},"i":{"x":0.67,"y":0},"s":[{"c":true,"i":[[0,0],[0,0],[0,0],[0,0],[85.99,-48.37],[125.82,0]],"o":[[0,0],[0,0],[0,0],[109.09,-2.2],[109.82,36.28],[0,0]],"v":[[170.18,411],[0,411],[0,0.02],[149.82,0.02],[206.54,191.72],[170.18,411]]}],"t":0},{"o":{"x":0.32,"y":0},"i":{"x":0.67,"y":0},"s":[{"c":true,"i":[[0,0],[0,0],[0,0],[0,0],[85.99,-48.37],[125.82,0]],"o":[[0,0],[0,0],[0,0],[109.09,-2.2],[109.82,36.28],[0,0]],"v":[[170.18,411],[0,411],[0,0.02],[149.82,0.02],[206.54,191.72],[170.18,411]]}],"t":33.06},{"o":{"x":0.32,"y":0},"i":{"x":0.67,"y":0},"s":[{"c":true,"i":[[0,0],[0,0],[0,0],[0,0],[85.99,-48.37],[125.82,0]],"o":[[0,0],[0,0],[0,0],[109.09,-2.2],[109.82,36.28],[0,0]],"v":[[170.18,411],[0,411],[0,0.02],[149.82,0.02],[206.54,191.72],[170.18,411]]}],"t":69},{"s":[{"c":true,"i":[[0,0],[0,0],[0,0],[0,0],[85.99,-48.37],[125.82,0]],"o":[[0,0],[0,0],[0,0],[109.09,-2.2],[109.82,36.28],[0,0]],"v":[[170.18,411],[0,411],[0,0.02],[149.82,0.02],[206.54,191.72],[170.18,411]]}],"t":129}]}},{"ty":"fl","bm":0,"hd":false,"nm":"","c":{"a":1,"k":[{"o":{"x":0.32,"y":0},"i":{"x":0.67,"y":0},"s":[0.9804,1,0.9647],"t":0},{"o":{"x":0.32,"y":0},"i":{"x":0.67,"y":0},"s":[0.9804,1,0.9647],"t":33.06},{"o":{"x":0.32,"y":0},"i":{"x":0.67,"y":0},"s":[0.9804,1,0.9647],"t":69},{"s":[0.9804,1,0.9647],"t":129}]},"r":1,"o":{"a":1,"k":[{"o":{"x":0.32,"y":0},"i":{"x":0.67,"y":0},"s":[100],"t":0},{"o":{"x":0.32,"y":0},"i":{"x":0.67,"y":0},"s":[100],"t":33.06},{"o":{"x":0.32,"y":0},"i":{"x":0.67,"y":0},"s":[100],"t":69},{"s":[100],"t":129}]}}],"ind":13},{"ty":4,"nm":"Ellipse 6065","sr":1,"st":0,"op":130.06,"ip":0,"hd":false,"ddd":0,"bm":0,"hasMask":false,"ao":0,"ks":{"a":{"a":1,"k":[{"o":{"x":0.32,"y":0},"i":{"x":0.67,"y":0},"s":[385.5,385.5],"t":0},{"o":{"x":0.32,"y":0},"i":{"x":0.67,"y":0},"s":[385.5,385.5],"t":33.06},{"o":{"x":0.32,"y":0},"i":{"x":0.67,"y":0},"s":[385.5,385.5],"t":69},{"s":[385.5,385.5],"t":129}]},"s":{"a":1,"k":[{"o":{"x":0.32,"y":0},"i":{"x":0.67,"y":0},"s":[100,100],"t":0},{"o":{"x":0.32,"y":0},"i":{"x":0.67,"y":0},"s":[100,100],"t":33.06},{"o":{"x":0.32,"y":0},"i":{"x":0.67,"y":0},"s":[100,100],"t":69},{"s":[100,100],"t":129}]},"sk":{"a":0,"k":0},"p":{"a":1,"k":[{"o":{"x":0.32,"y":0},"i":{"x":0.67,"y":0},"s":[554.5,554.5],"t":0},{"o":{"x":0.32,"y":0},"i":{"x":0.67,"y":0},"s":[554.5,554.5],"t":33.06},{"o":{"x":0.32,"y":0},"i":{"x":0.67,"y":0},"s":[554.5,554.5],"t":69},{"s":[554.5,554.5],"t":129}]},"r":{"a":1,"k":[{"o":{"x":0.32,"y":0},"i":{"x":0.67,"y":0},"s":[0],"t":0},{"o":{"x":0.32,"y":0},"i":{"x":0.67,"y":0},"s":[0],"t":33.06},{"o":{"x":0.32,"y":0},"i":{"x":0.67,"y":0},"s":[0],"t":69},{"s":[0],"t":129}]},"sa":{"a":0,"k":0},"o":{"a":1,"k":[{"o":{"x":0.32,"y":0},"i":{"x":0.67,"y":0},"s":[0],"t":0},{"o":{"x":0.32,"y":0},"i":{"x":0.67,"y":0},"s":[0],"t":33.06},{"o":{"x":0.32,"y":0},"i":{"x":0.67,"y":0},"s":[100],"t":69},{"s":[100],"t":129}]}},"shapes":[{"ty":"sh","bm":0,"hd":false,"nm":"","d":1,"ks":{"a":1,"k":[{"o":{"x":0.32,"y":0},"i":{"x":0.67,"y":0},"s":[{"c":true,"i":[[0,0],[212.91,0],[0,212.91],[-212.91,0],[0,-212.91]],"o":[[0,212.91],[-212.91,0],[0,-212.91],[212.91,0],[0,0]],"v":[[771,385.5],[385.5,771],[0,385.5],[385.5,0],[771,385.5]]}],"t":0},{"o":{"x":0.32,"y":0},"i":{"x":0.67,"y":0},"s":[{"c":true,"i":[[0,0],[212.91,0],[0,212.91],[-212.91,0],[0,-212.91]],"o":[[0,212.91],[-212.91,0],[0,-212.91],[212.91,0],[0,0]],"v":[[771,385.5],[385.5,771],[0,385.5],[385.5,0],[771,385.5]]}],"t":33.06},{"o":{"x":0.32,"y":0},"i":{"x":0.67,"y":0},"s":[{"c":true,"i":[[0,0],[212.91,0],[0,212.91],[-212.91,0],[0,-212.91]],"o":[[0,212.91],[-212.91,0],[0,-212.91],[212.91,0],[0,0]],"v":[[771,385.5],[385.5,771],[0,385.5],[385.5,0],[771,385.5]]}],"t":69},{"s":[{"c":true,"i":[[0,0],[212.91,0],[0,212.91],[-212.91,0],[0,-212.91]],"o":[[0,212.91],[-212.91,0],[0,-212.91],[212.91,0],[0,0]],"v":[[771,385.5],[385.5,771],[0,385.5],[385.5,0],[771,385.5]]}],"t":129}]}},{"ty":"fl","bm":0,"hd":false,"nm":"","c":{"a":1,"k":[{"o":{"x":0.32,"y":0},"i":{"x":0.67,"y":0},"s":[0.2902,0.6,0.3765],"t":0},{"o":{"x":0.32,"y":0},"i":{"x":0.67,"y":0},"s":[0.2902,0.6,0.3765],"t":33.06},{"o":{"x":0.32,"y":0},"i":{"x":0.67,"y":0},"s":[0.2902,0.6,0.3765],"t":69},{"s":[0.2902,0.6,0.3765],"t":129}]},"r":1,"o":{"a":1,"k":[{"o":{"x":0.32,"y":0},"i":{"x":0.67,"y":0},"s":[100],"t":0},{"o":{"x":0.32,"y":0},"i":{"x":0.67,"y":0},"s":[100],"t":33.06},{"o":{"x":0.32,"y":0},"i":{"x":0.67,"y":0},"s":[100],"t":69},{"s":[100],"t":129}]}}],"ind":14},{"ty":4,"nm":"Frame 76078 Bg","sr":1,"st":0,"op":130.06,"ip":0,"hd":false,"ddd":0,"bm":0,"hasMask":false,"ao":0,"ks":{"a":{"a":1,"k":[{"o":{"x":0.32,"y":0},"i":{"x":0.67,"y":0},"s":[555,555],"t":0},{"o":{"x":0.32,"y":0},"i":{"x":0.67,"y":0},"s":[555,555],"t":0.06},{"o":{"x":0.32,"y":0},"i":{"x":0.67,"y":0},"s":[555,555],"t":12},{"o":{"x":0.32,"y":0},"i":{"x":0.67,"y":0},"s":[555,555],"t":18},{"o":{"x":0.32,"y":0},"i":{"x":0.67,"y":0},"s":[555,555],"t":21},{"o":{"x":0.32,"y":0},"i":{"x":0.67,"y":0},"s":[555,555],"t":24},{"o":{"x":0.32,"y":0},"i":{"x":0.67,"y":0},"s":[555,555],"t":27},{"o":{"x":0.32,"y":0},"i":{"x":0.67,"y":0},"s":[555,555],"t":30},{"o":{"x":0.32,"y":0},"i":{"x":0.67,"y":0},"s":[555,555],"t":33},{"s":[555,555],"t":69}]},"s":{"a":1,"k":[{"o":{"x":0.32,"y":0},"i":{"x":0.67,"y":0},"s":[100,100],"t":0},{"o":{"x":0.32,"y":0},"i":{"x":0.67,"y":0},"s":[100,100],"t":0.06},{"o":{"x":0.32,"y":0},"i":{"x":0.67,"y":0},"s":[100,100],"t":12},{"o":{"x":0.32,"y":0},"i":{"x":0.67,"y":0},"s":[100,100],"t":18},{"o":{"x":0.32,"y":0},"i":{"x":0.67,"y":0},"s":[100,100],"t":21},{"o":{"x":0.32,"y":0},"i":{"x":0.67,"y":0},"s":[100,100],"t":24},{"o":{"x":0.32,"y":0},"i":{"x":0.67,"y":0},"s":[100,100],"t":27},{"o":{"x":0.32,"y":0},"i":{"x":0.67,"y":0},"s":[100,100],"t":30},{"o":{"x":0.32,"y":0},"i":{"x":0.67,"y":0},"s":[100,100],"t":33},{"s":[100,100],"t":69}]},"sk":{"a":0,"k":0},"p":{"a":1,"k":[{"o":{"x":0.32,"y":0},"i":{"x":0.67,"y":0},"s":[555,555],"t":0},{"o":{"x":0.32,"y":0},"i":{"x":0.67,"y":0},"s":[555,555],"t":0.06},{"o":{"x":0.32,"y":0},"i":{"x":0.67,"y":0},"s":[555,555],"t":12},{"o":{"x":0.32,"y":0},"i":{"x":0.67,"y":0},"s":[555,555],"t":18},{"o":{"x":0.32,"y":0},"i":{"x":0.67,"y":0},"s":[555,555],"t":21},{"o":{"x":0.32,"y":0},"i":{"x":0.67,"y":0},"s":[555,555],"t":24},{"o":{"x":0.32,"y":0},"i":{"x":0.67,"y":0},"s":[555,555],"t":27},{"o":{"x":0.32,"y":0},"i":{"x":0.67,"y":0},"s":[555,555],"t":30},{"o":{"x":0.32,"y":0},"i":{"x":0.67,"y":0},"s":[555,555],"t":33},{"s":[555,555],"t":69}]},"r":{"a":1,"k":[{"o":{"x":0.32,"y":0},"i":{"x":0.67,"y":0},"s":[0],"t":0},{"o":{"x":0.32,"y":0},"i":{"x":0.67,"y":0},"s":[0],"t":0.06},{"o":{"x":0.32,"y":0},"i":{"x":0.67,"y":0},"s":[0],"t":12},{"o":{"x":0.32,"y":0},"i":{"x":0.67,"y":0},"s":[0],"t":18},{"o":{"x":0.32,"y":0},"i":{"x":0.67,"y":0},"s":[0],"t":21},{"o":{"x":0.32,"y":0},"i":{"x":0.67,"y":0},"s":[0],"t":24},{"o":{"x":0.32,"y":0},"i":{"x":0.67,"y":0},"s":[0],"t":27},{"o":{"x":0.32,"y":0},"i":{"x":0.67,"y":0},"s":[0],"t":30},{"o":{"x":0.32,"y":0},"i":{"x":0.67,"y":0},"s":[0],"t":33},{"s":[0],"t":69}]},"sa":{"a":0,"k":0},"o":{"a":1,"k":[{"o":{"x":0.32,"y":0},"i":{"x":0.67,"y":0},"s":[100],"t":0},{"o":{"x":0.32,"y":0},"i":{"x":0.67,"y":0},"s":[100],"t":0.06},{"o":{"x":0.32,"y":0},"i":{"x":0.67,"y":0},"s":[100],"t":12},{"o":{"x":0.32,"y":0},"i":{"x":0.67,"y":0},"s":[100],"t":18},{"o":{"x":0.32,"y":0},"i":{"x":0.67,"y":0},"s":[100],"t":21},{"o":{"x":0.32,"y":0},"i":{"x":0.67,"y":0},"s":[100],"t":24},{"o":{"x":0.32,"y":0},"i":{"x":0.67,"y":0},"s":[100],"t":27},{"o":{"x":0.32,"y":0},"i":{"x":0.67,"y":0},"s":[100],"t":30},{"o":{"x":0.32,"y":0},"i":{"x":0.67,"y":0},"s":[100],"t":33},{"s":[100],"t":69}]}},"shapes":[{"ty":"sh","bm":0,"hd":false,"nm":"","d":1,"ks":{"a":1,"k":[{"o":{"x":0.32,"y":0},"i":{"x":0.67,"y":0},"s":[{"c":true,"i":[[0,0],[0,0],[0,0],[0,0]],"o":[[0,0],[0,0],[0,0],[0,0]],"v":[[1110,0],[1110,1110],[0,1110],[0,0]]}],"t":0},{"o":{"x":0.32,"y":0},"i":{"x":0.67,"y":0},"s":[{"c":true,"i":[[0,0],[0,0],[0,0],[0,0]],"o":[[0,0],[0,0],[0,0],[0,0]],"v":[[1110,0],[1110,1110],[0,1110],[0,0]]}],"t":0.06},{"o":{"x":0.32,"y":0},"i":{"x":0.67,"y":0},"s":[{"c":true,"i":[[0,0],[0,0],[0,0],[0,0]],"o":[[0,0],[0,0],[0,0],[0,0]],"v":[[1110,0],[1110,1110],[0,1110],[0,0]]}],"t":12},{"o":{"x":0.32,"y":0},"i":{"x":0.67,"y":0},"s":[{"c":true,"i":[[0,0],[0,0],[0,0],[0,0]],"o":[[0,0],[0,0],[0,0],[0,0]],"v":[[1110,0],[1110,1110],[0,1110],[0,0]]}],"t":18},{"o":{"x":0.32,"y":0},"i":{"x":0.67,"y":0},"s":[{"c":true,"i":[[0,0],[0,0],[0,0],[0,0]],"o":[[0,0],[0,0],[0,0],[0,0]],"v":[[1110,0],[1110,1110],[0,1110],[0,0]]}],"t":21},{"o":{"x":0.32,"y":0},"i":{"x":0.67,"y":0},"s":[{"c":true,"i":[[0,0],[0,0],[0,0],[0,0]],"o":[[0,0],[0,0],[0,0],[0,0]],"v":[[1110,0],[1110,1110],[0,1110],[0,0]]}],"t":24},{"o":{"x":0.32,"y":0},"i":{"x":0.67,"y":0},"s":[{"c":true,"i":[[0,0],[0,0],[0,0],[0,0]],"o":[[0,0],[0,0],[0,0],[0,0]],"v":[[1110,0],[1110,1110],[0,1110],[0,0]]}],"t":27},{"o":{"x":0.32,"y":0},"i":{"x":0.67,"y":0},"s":[{"c":true,"i":[[0,0],[0,0],[0,0],[0,0]],"o":[[0,0],[0,0],[0,0],[0,0]],"v":[[1110,0],[1110,1110],[0,1110],[0,0]]}],"t":30},{"o":{"x":0.32,"y":0},"i":{"x":0.67,"y":0},"s":[{"c":true,"i":[[0,0],[0,0],[0,0],[0,0]],"o":[[0,0],[0,0],[0,0],[0,0]],"v":[[1110,0],[1110,1110],[0,1110],[0,0]]}],"t":33},{"s":[{"c":true,"i":[[0,0],[0,0],[0,0],[0,0]],"o":[[0,0],[0,0],[0,0],[0,0]],"v":[[1110,0],[1110,1110],[0,1110],[0,0]]}],"t":69}]}},{"ty":"fl","bm":0,"hd":false,"nm":"","c":{"a":1,"k":[{"o":{"x":0.32,"y":0},"i":{"x":0.67,"y":0},"s":[0.9804,1,0.9647],"t":0},{"o":{"x":0.32,"y":0},"i":{"x":0.67,"y":0},"s":[0.9804,1,0.9647],"t":0.06},{"o":{"x":0.32,"y":0},"i":{"x":0.67,"y":0},"s":[0.9804,1,0.9647],"t":12},{"o":{"x":0.32,"y":0},"i":{"x":0.67,"y":0},"s":[0.9804,1,0.9647],"t":18},{"o":{"x":0.32,"y":0},"i":{"x":0.67,"y":0},"s":[0.9804,1,0.9647],"t":21},{"o":{"x":0.32,"y":0},"i":{"x":0.67,"y":0},"s":[0.9804,1,0.9647],"t":24},{"o":{"x":0.32,"y":0},"i":{"x":0.67,"y":0},"s":[0.9804,1,0.9647],"t":27},{"o":{"x":0.32,"y":0},"i":{"x":0.67,"y":0},"s":[0.9804,1,0.9647],"t":30},{"o":{"x":0.32,"y":0},"i":{"x":0.67,"y":0},"s":[0.9804,1,0.9647],"t":33},{"s":[0.9804,1,0.9647],"t":69}]},"r":1,"o":{"a":1,"k":[{"o":{"x":0.32,"y":0},"i":{"x":0.67,"y":0},"s":[100],"t":0},{"o":{"x":0.32,"y":0},"i":{"x":0.67,"y":0},"s":[100],"t":0.06},{"o":{"x":0.32,"y":0},"i":{"x":0.67,"y":0},"s":[100],"t":12},{"o":{"x":0.32,"y":0},"i":{"x":0.67,"y":0},"s":[100],"t":18},{"o":{"x":0.32,"y":0},"i":{"x":0.67,"y":0},"s":[100],"t":21},{"o":{"x":0.32,"y":0},"i":{"x":0.67,"y":0},"s":[100],"t":24},{"o":{"x":0.32,"y":0},"i":{"x":0.67,"y":0},"s":[100],"t":27},{"o":{"x":0.32,"y":0},"i":{"x":0.67,"y":0},"s":[100],"t":30},{"o":{"x":0.32,"y":0},"i":{"x":0.67,"y":0},"s":[100],"t":33},{"s":[100],"t":69}]}}],"ind":15}],"v":"5.7.0","fr":60,"op":129.06,"ip":0,"assets":[]}